{
  "schemaVersion": "report-seed-tag-map-v1",
  "updatedAt": "2026-05-14",
  "status": "seed-data-only-not-applied",
  "bySubject": {
    "경제": [
      {
        "seedId": "RPT-004",
        "seedName": "사회문제·정책 거버넌스 평가형",
        "stage": "stage1"
      },
      {
        "seedId": "RPT-009",
        "seedName": "의료사회복지·위기개입 정책 설계형",
        "stage": "stage2"
      }
    ],
    "국어": [
      {
        "seedId": "RPT-010",
        "seedName": "미시-거시 구조 비교·정치사회 데이터 분석형",
        "stage": "stage2"
      }
    ],
    "물리학": [
      {
        "seedId": "RPT-001",
        "seedName": "시스템·데이터 기반 위험 예측형",
        "stage": "stage1"
      },
      {
        "seedId": "RPT-002",
        "seedName": "지속가능성·소재·디자인 해결형",
        "stage": "stage1"
      },
      {
        "seedId": "RPT-005",
        "seedName": "공간 데이터·도시 최적화 모델링형",
        "stage": "stage1"
      }
    ],
    "물리학Ⅰ": [
      {
        "seedId": "RPT-008",
        "seedName": "핵에너지·물리 원리 기반 시스템 안전형",
        "stage": "stage2"
      }
    ],
    "물리학Ⅱ": [
      {
        "seedId": "RPT-008",
        "seedName": "핵에너지·물리 원리 기반 시스템 안전형",
        "stage": "stage2"
      }
    ],
    "물질과 에너지": [
      {
        "seedId": "RPT-006",
        "seedName": "바이오매스·전기화학 촉매 전환형",
        "stage": "stage2"
      }
    ],
    "미술/디자인": [
      {
        "seedId": "RPT-002",
        "seedName": "지속가능성·소재·디자인 해결형",
        "stage": "stage1"
      }
    ],
    "보건": [
      {
        "seedId": "RPT-007",
        "seedName": "분자기전·질병 메커니즘 해석형",
        "stage": "stage2"
      },
      {
        "seedId": "RPT-009",
        "seedName": "의료사회복지·위기개입 정책 설계형",
        "stage": "stage2"
      }
    ],
    "사회·문화": [
      {
        "seedId": "RPT-004",
        "seedName": "사회문제·정책 거버넌스 평가형",
        "stage": "stage1"
      },
      {
        "seedId": "RPT-009",
        "seedName": "의료사회복지·위기개입 정책 설계형",
        "stage": "stage2"
      },
      {
        "seedId": "RPT-010",
        "seedName": "미시-거시 구조 비교·정치사회 데이터 분석형",
        "stage": "stage2"
      }
    ],
    "생명과학Ⅰ": [
      {
        "seedId": "RPT-007",
        "seedName": "분자기전·질병 메커니즘 해석형",
        "stage": "stage2"
      }
    ],
    "생명과학Ⅱ": [
      {
        "seedId": "RPT-007",
        "seedName": "분자기전·질병 메커니즘 해석형",
        "stage": "stage2"
      }
    ],
    "생활과 윤리": [
      {
        "seedId": "RPT-009",
        "seedName": "의료사회복지·위기개입 정책 설계형",
        "stage": "stage2"
      }
    ],
    "수학": [
      {
        "seedId": "RPT-001",
        "seedName": "시스템·데이터 기반 위험 예측형",
        "stage": "stage1"
      },
      {
        "seedId": "RPT-002",
        "seedName": "지속가능성·소재·디자인 해결형",
        "stage": "stage1"
      },
      {
        "seedId": "RPT-003",
        "seedName": "지구시스템·기후 데이터 해석형",
        "stage": "stage1"
      },
      {
        "seedId": "RPT-005",
        "seedName": "공간 데이터·도시 최적화 모델링형",
        "stage": "stage1"
      },
      {
        "seedId": "RPT-006",
        "seedName": "바이오매스·전기화학 촉매 전환형",
        "stage": "stage2"
      },
      {
        "seedId": "RPT-008",
        "seedName": "핵에너지·물리 원리 기반 시스템 안전형",
        "stage": "stage2"
      }
    ],
    "정보": [
      {
        "seedId": "RPT-001",
        "seedName": "시스템·데이터 기반 위험 예측형",
        "stage": "stage1"
      },
      {
        "seedId": "RPT-005",
        "seedName": "공간 데이터·도시 최적화 모델링형",
        "stage": "stage1"
      }
    ],
    "정치와 법": [
      {
        "seedId": "RPT-004",
        "seedName": "사회문제·정책 거버넌스 평가형",
        "stage": "stage1"
      },
      {
        "seedId": "RPT-009",
        "seedName": "의료사회복지·위기개입 정책 설계형",
        "stage": "stage2"
      },
      {
        "seedId": "RPT-010",
        "seedName": "미시-거시 구조 비교·정치사회 데이터 분석형",
        "stage": "stage2"
      }
    ],
    "지구과학": [
      {
        "seedId": "RPT-001",
        "seedName": "시스템·데이터 기반 위험 예측형",
        "stage": "stage1"
      },
      {
        "seedId": "RPT-003",
        "seedName": "지구시스템·기후 데이터 해석형",
        "stage": "stage1"
      }
    ],
    "통합과학": [
      {
        "seedId": "RPT-001",
        "seedName": "시스템·데이터 기반 위험 예측형",
        "stage": "stage1"
      },
      {
        "seedId": "RPT-002",
        "seedName": "지속가능성·소재·디자인 해결형",
        "stage": "stage1"
      },
      {
        "seedId": "RPT-003",
        "seedName": "지구시스템·기후 데이터 해석형",
        "stage": "stage1"
      },
      {
        "seedId": "RPT-006",
        "seedName": "바이오매스·전기화학 촉매 전환형",
        "stage": "stage2"
      },
      {
        "seedId": "RPT-007",
        "seedName": "분자기전·질병 메커니즘 해석형",
        "stage": "stage2"
      },
      {
        "seedId": "RPT-008",
        "seedName": "핵에너지·물리 원리 기반 시스템 안전형",
        "stage": "stage2"
      }
    ],
    "통합사회": [
      {
        "seedId": "RPT-004",
        "seedName": "사회문제·정책 거버넌스 평가형",
        "stage": "stage1"
      },
      {
        "seedId": "RPT-010",
        "seedName": "미시-거시 구조 비교·정치사회 데이터 분석형",
        "stage": "stage2"
      }
    ],
    "한국지리": [
      {
        "seedId": "RPT-004",
        "seedName": "사회문제·정책 거버넌스 평가형",
        "stage": "stage1"
      },
      {
        "seedId": "RPT-005",
        "seedName": "공간 데이터·도시 최적화 모델링형",
        "stage": "stage1"
      }
    ],
    "화학Ⅰ": [
      {
        "seedId": "RPT-006",
        "seedName": "바이오매스·전기화학 촉매 전환형",
        "stage": "stage2"
      },
      {
        "seedId": "RPT-007",
        "seedName": "분자기전·질병 메커니즘 해석형",
        "stage": "stage2"
      }
    ],
    "화학Ⅱ": [
      {
        "seedId": "RPT-006",
        "seedName": "바이오매스·전기화학 촉매 전환형",
        "stage": "stage2"
      }
    ],
    "확률과 통계": [
      {
        "seedId": "RPT-003",
        "seedName": "지구시스템·기후 데이터 해석형",
        "stage": "stage1"
      },
      {
        "seedId": "RPT-005",
        "seedName": "공간 데이터·도시 최적화 모델링형",
        "stage": "stage1"
      },
      {
        "seedId": "RPT-008",
        "seedName": "핵에너지·물리 원리 기반 시스템 안전형",
        "stage": "stage2"
      },
      {
        "seedId": "RPT-010",
        "seedName": "미시-거시 구조 비교·정치사회 데이터 분석형",
        "stage": "stage2"
      }
    ],
    "환경": [
      {
        "seedId": "RPT-002",
        "seedName": "지속가능성·소재·디자인 해결형",
        "stage": "stage1"
      },
      {
        "seedId": "RPT-003",
        "seedName": "지구시스템·기후 데이터 해석형",
        "stage": "stage1"
      },
      {
        "seedId": "RPT-006",
        "seedName": "바이오매스·전기화학 촉매 전환형",
        "stage": "stage2"
      }
    ]
  },
  "byMajor": {
    "AI": [
      {
        "seedId": "RPT-001",
        "seedName": "시스템·데이터 기반 위험 예측형",
        "stage": "stage1"
      }
    ],
    "간호학": [
      {
        "seedId": "RPT-009",
        "seedName": "의료사회복지·위기개입 정책 설계형",
        "stage": "stage2"
      }
    ],
    "건설안전공학": [
      {
        "seedId": "RPT-001",
        "seedName": "시스템·데이터 기반 위험 예측형",
        "stage": "stage1"
      }
    ],
    "건축공학": [
      {
        "seedId": "RPT-001",
        "seedName": "시스템·데이터 기반 위험 예측형",
        "stage": "stage1"
      }
    ],
    "공간정보공학": [
      {
        "seedId": "RPT-001",
        "seedName": "시스템·데이터 기반 위험 예측형",
        "stage": "stage1"
      },
      {
        "seedId": "RPT-005",
        "seedName": "공간 데이터·도시 최적화 모델링형",
        "stage": "stage1"
      }
    ],
    "공공정책": [
      {
        "seedId": "RPT-004",
        "seedName": "사회문제·정책 거버넌스 평가형",
        "stage": "stage1"
      },
      {
        "seedId": "RPT-009",
        "seedName": "의료사회복지·위기개입 정책 설계형",
        "stage": "stage2"
      },
      {
        "seedId": "RPT-010",
        "seedName": "미시-거시 구조 비교·정치사회 데이터 분석형",
        "stage": "stage2"
      }
    ],
    "교육행정": [
      {
        "seedId": "RPT-004",
        "seedName": "사회문제·정책 거버넌스 평가형",
        "stage": "stage1"
      }
    ],
    "교통공학": [
      {
        "seedId": "RPT-005",
        "seedName": "공간 데이터·도시 최적화 모델링형",
        "stage": "stage1"
      }
    ],
    "기계공학": [
      {
        "seedId": "RPT-008",
        "seedName": "핵에너지·물리 원리 기반 시스템 안전형",
        "stage": "stage2"
      }
    ],
    "기후과학": [
      {
        "seedId": "RPT-003",
        "seedName": "지구시스템·기후 데이터 해석형",
        "stage": "stage1"
      }
    ],
    "나노소재공학": [
      {
        "seedId": "RPT-006",
        "seedName": "바이오매스·전기화학 촉매 전환형",
        "stage": "stage2"
      }
    ],
    "대기과학": [
      {
        "seedId": "RPT-003",
        "seedName": "지구시스템·기후 데이터 해석형",
        "stage": "stage1"
      }
    ],
    "데이터과학": [
      {
        "seedId": "RPT-001",
        "seedName": "시스템·데이터 기반 위험 예측형",
        "stage": "stage1"
      },
      {
        "seedId": "RPT-003",
        "seedName": "지구시스템·기후 데이터 해석형",
        "stage": "stage1"
      }
    ],
    "데이터사회과학": [
      {
        "seedId": "RPT-010",
        "seedName": "미시-거시 구조 비교·정치사회 데이터 분석형",
        "stage": "stage2"
      }
    ],
    "도시계획학": [
      {
        "seedId": "RPT-005",
        "seedName": "공간 데이터·도시 최적화 모델링형",
        "stage": "stage1"
      }
    ],
    "도시공학": [
      {
        "seedId": "RPT-005",
        "seedName": "공간 데이터·도시 최적화 모델링형",
        "stage": "stage1"
      }
    ],
    "도시행정": [
      {
        "seedId": "RPT-004",
        "seedName": "사회문제·정책 거버넌스 평가형",
        "stage": "stage1"
      }
    ],
    "물리학": [
      {
        "seedId": "RPT-008",
        "seedName": "핵에너지·물리 원리 기반 시스템 안전형",
        "stage": "stage2"
      }
    ],
    "보건행정": [
      {
        "seedId": "RPT-009",
        "seedName": "의료사회복지·위기개입 정책 설계형",
        "stage": "stage2"
      }
    ],
    "분자생물학": [
      {
        "seedId": "RPT-007",
        "seedName": "분자기전·질병 메커니즘 해석형",
        "stage": "stage2"
      }
    ],
    "사회복지학": [
      {
        "seedId": "RPT-009",
        "seedName": "의료사회복지·위기개입 정책 설계형",
        "stage": "stage2"
      }
    ],
    "사회학": [
      {
        "seedId": "RPT-010",
        "seedName": "미시-거시 구조 비교·정치사회 데이터 분석형",
        "stage": "stage2"
      }
    ],
    "산업디자인": [
      {
        "seedId": "RPT-002",
        "seedName": "지속가능성·소재·디자인 해결형",
        "stage": "stage1"
      }
    ],
    "상담심리": [
      {
        "seedId": "RPT-009",
        "seedName": "의료사회복지·위기개입 정책 설계형",
        "stage": "stage2"
      }
    ],
    "생명공학": [
      {
        "seedId": "RPT-007",
        "seedName": "분자기전·질병 메커니즘 해석형",
        "stage": "stage2"
      }
    ],
    "생명과학": [
      {
        "seedId": "RPT-007",
        "seedName": "분자기전·질병 메커니즘 해석형",
        "stage": "stage2"
      }
    ],
    "섬유공학": [
      {
        "seedId": "RPT-002",
        "seedName": "지속가능성·소재·디자인 해결형",
        "stage": "stage1"
      }
    ],
    "스마트시티": [
      {
        "seedId": "RPT-005",
        "seedName": "공간 데이터·도시 최적화 모델링형",
        "stage": "stage1"
      }
    ],
    "신경과학": [
      {
        "seedId": "RPT-007",
        "seedName": "분자기전·질병 메커니즘 해석형",
        "stage": "stage2"
      }
    ],
    "신소재공학": [
      {
        "seedId": "RPT-006",
        "seedName": "바이오매스·전기화학 촉매 전환형",
        "stage": "stage2"
      }
    ],
    "안전공학": [
      {
        "seedId": "RPT-001",
        "seedName": "시스템·데이터 기반 위험 예측형",
        "stage": "stage1"
      }
    ],
    "약학": [
      {
        "seedId": "RPT-007",
        "seedName": "분자기전·질병 메커니즘 해석형",
        "stage": "stage2"
      }
    ],
    "언론정보학": [
      {
        "seedId": "RPT-010",
        "seedName": "미시-거시 구조 비교·정치사회 데이터 분석형",
        "stage": "stage2"
      }
    ],
    "에너지공학": [
      {
        "seedId": "RPT-006",
        "seedName": "바이오매스·전기화학 촉매 전환형",
        "stage": "stage2"
      },
      {
        "seedId": "RPT-008",
        "seedName": "핵에너지·물리 원리 기반 시스템 안전형",
        "stage": "stage2"
      }
    ],
    "원자력공학": [
      {
        "seedId": "RPT-008",
        "seedName": "핵에너지·물리 원리 기반 시스템 안전형",
        "stage": "stage2"
      }
    ],
    "의료사회복지": [
      {
        "seedId": "RPT-009",
        "seedName": "의료사회복지·위기개입 정책 설계형",
        "stage": "stage2"
      }
    ],
    "의류학": [
      {
        "seedId": "RPT-002",
        "seedName": "지속가능성·소재·디자인 해결형",
        "stage": "stage1"
      }
    ],
    "의생명과학": [
      {
        "seedId": "RPT-007",
        "seedName": "분자기전·질병 메커니즘 해석형",
        "stage": "stage2"
      }
    ],
    "의학": [
      {
        "seedId": "RPT-007",
        "seedName": "분자기전·질병 메커니즘 해석형",
        "stage": "stage2"
      }
    ],
    "재료공학": [
      {
        "seedId": "RPT-006",
        "seedName": "바이오매스·전기화학 촉매 전환형",
        "stage": "stage2"
      }
    ],
    "전력공학": [
      {
        "seedId": "RPT-008",
        "seedName": "핵에너지·물리 원리 기반 시스템 안전형",
        "stage": "stage2"
      }
    ],
    "정책학": [
      {
        "seedId": "RPT-004",
        "seedName": "사회문제·정책 거버넌스 평가형",
        "stage": "stage1"
      }
    ],
    "정치외교학": [
      {
        "seedId": "RPT-010",
        "seedName": "미시-거시 구조 비교·정치사회 데이터 분석형",
        "stage": "stage2"
      }
    ],
    "지구과학": [
      {
        "seedId": "RPT-003",
        "seedName": "지구시스템·기후 데이터 해석형",
        "stage": "stage1"
      }
    ],
    "지리학": [
      {
        "seedId": "RPT-005",
        "seedName": "공간 데이터·도시 최적화 모델링형",
        "stage": "stage1"
      }
    ],
    "지방자치": [
      {
        "seedId": "RPT-004",
        "seedName": "사회문제·정책 거버넌스 평가형",
        "stage": "stage1"
      }
    ],
    "지속가능디자인": [
      {
        "seedId": "RPT-002",
        "seedName": "지속가능성·소재·디자인 해결형",
        "stage": "stage1"
      }
    ],
    "토목공학": [
      {
        "seedId": "RPT-001",
        "seedName": "시스템·데이터 기반 위험 예측형",
        "stage": "stage1"
      }
    ],
    "패션디자인": [
      {
        "seedId": "RPT-002",
        "seedName": "지속가능성·소재·디자인 해결형",
        "stage": "stage1"
      }
    ],
    "해양학": [
      {
        "seedId": "RPT-003",
        "seedName": "지구시스템·기후 데이터 해석형",
        "stage": "stage1"
      }
    ],
    "행정학": [
      {
        "seedId": "RPT-004",
        "seedName": "사회문제·정책 거버넌스 평가형",
        "stage": "stage1"
      },
      {
        "seedId": "RPT-010",
        "seedName": "미시-거시 구조 비교·정치사회 데이터 분석형",
        "stage": "stage2"
      }
    ],
    "화학공학": [
      {
        "seedId": "RPT-006",
        "seedName": "바이오매스·전기화학 촉매 전환형",
        "stage": "stage2"
      }
    ],
    "환경공학": [
      {
        "seedId": "RPT-002",
        "seedName": "지속가능성·소재·디자인 해결형",
        "stage": "stage1"
      },
      {
        "seedId": "RPT-003",
        "seedName": "지구시스템·기후 데이터 해석형",
        "stage": "stage1"
      },
      {
        "seedId": "RPT-006",
        "seedName": "바이오매스·전기화학 촉매 전환형",
        "stage": "stage2"
      }
    ],
    "환경에너지공학": [
      {
        "seedId": "RPT-008",
        "seedName": "핵에너지·물리 원리 기반 시스템 안전형",
        "stage": "stage2"
      }
    ]
  },
  "byAxisTrigger": {
    "SMR": [
      {
        "seedId": "RPT-008",
        "seedName": "핵에너지·물리 원리 기반 시스템 안전형",
        "stage": "stage2"
      }
    ],
    "거버넌스": [
      {
        "seedId": "RPT-004",
        "seedName": "사회문제·정책 거버넌스 평가형",
        "stage": "stage1"
      }
    ],
    "공간": [
      {
        "seedId": "RPT-005",
        "seedName": "공간 데이터·도시 최적화 모델링형",
        "stage": "stage1"
      }
    ],
    "공공서비스": [
      {
        "seedId": "RPT-009",
        "seedName": "의료사회복지·위기개입 정책 설계형",
        "stage": "stage2"
      }
    ],
    "공공성": [
      {
        "seedId": "RPT-004",
        "seedName": "사회문제·정책 거버넌스 평가형",
        "stage": "stage1"
      }
    ],
    "공학 적용": [
      {
        "seedId": "RPT-001",
        "seedName": "시스템·데이터 기반 위험 예측형",
        "stage": "stage1"
      }
    ],
    "구조분석": [
      {
        "seedId": "RPT-010",
        "seedName": "미시-거시 구조 비교·정치사회 데이터 분석형",
        "stage": "stage2"
      }
    ],
    "균열": [
      {
        "seedId": "RPT-010",
        "seedName": "미시-거시 구조 비교·정치사회 데이터 분석형",
        "stage": "stage2"
      }
    ],
    "기후변화": [
      {
        "seedId": "RPT-003",
        "seedName": "지구시스템·기후 데이터 해석형",
        "stage": "stage1"
      }
    ],
    "단백질": [
      {
        "seedId": "RPT-007",
        "seedName": "분자기전·질병 메커니즘 해석형",
        "stage": "stage2"
      }
    ],
    "데이터": [
      {
        "seedId": "RPT-005",
        "seedName": "공간 데이터·도시 최적화 모델링형",
        "stage": "stage1"
      }
    ],
    "데이터 지표": [
      {
        "seedId": "RPT-010",
        "seedName": "미시-거시 구조 비교·정치사회 데이터 분석형",
        "stage": "stage2"
      }
    ],
    "데이터 해석": [
      {
        "seedId": "RPT-001",
        "seedName": "시스템·데이터 기반 위험 예측형",
        "stage": "stage1"
      }
    ],
    "도시": [
      {
        "seedId": "RPT-005",
        "seedName": "공간 데이터·도시 최적화 모델링형",
        "stage": "stage1"
      }
    ],
    "디자인": [
      {
        "seedId": "RPT-002",
        "seedName": "지속가능성·소재·디자인 해결형",
        "stage": "stage1"
      }
    ],
    "모델링": [
      {
        "seedId": "RPT-001",
        "seedName": "시스템·데이터 기반 위험 예측형",
        "stage": "stage1"
      },
      {
        "seedId": "RPT-005",
        "seedName": "공간 데이터·도시 최적화 모델링형",
        "stage": "stage1"
      }
    ],
    "반응 선택성": [
      {
        "seedId": "RPT-006",
        "seedName": "바이오매스·전기화학 촉매 전환형",
        "stage": "stage2"
      }
    ],
    "복지제도": [
      {
        "seedId": "RPT-009",
        "seedName": "의료사회복지·위기개입 정책 설계형",
        "stage": "stage2"
      }
    ],
    "분자기전": [
      {
        "seedId": "RPT-007",
        "seedName": "분자기전·질병 메커니즘 해석형",
        "stage": "stage2"
      }
    ],
    "비교평가": [
      {
        "seedId": "RPT-010",
        "seedName": "미시-거시 구조 비교·정치사회 데이터 분석형",
        "stage": "stage2"
      }
    ],
    "비용-편익": [
      {
        "seedId": "RPT-009",
        "seedName": "의료사회복지·위기개입 정책 설계형",
        "stage": "stage2"
      }
    ],
    "비용편익": [
      {
        "seedId": "RPT-004",
        "seedName": "사회문제·정책 거버넌스 평가형",
        "stage": "stage1"
      }
    ],
    "사례관리": [
      {
        "seedId": "RPT-009",
        "seedName": "의료사회복지·위기개입 정책 설계형",
        "stage": "stage2"
      }
    ],
    "사회문제": [
      {
        "seedId": "RPT-004",
        "seedName": "사회문제·정책 거버넌스 평가형",
        "stage": "stage1"
      },
      {
        "seedId": "RPT-010",
        "seedName": "미시-거시 구조 비교·정치사회 데이터 분석형",
        "stage": "stage2"
      }
    ],
    "산화환원": [
      {
        "seedId": "RPT-006",
        "seedName": "바이오매스·전기화학 촉매 전환형",
        "stage": "stage2"
      }
    ],
    "상담": [
      {
        "seedId": "RPT-009",
        "seedName": "의료사회복지·위기개입 정책 설계형",
        "stage": "stage2"
      }
    ],
    "생활 문제": [
      {
        "seedId": "RPT-002",
        "seedName": "지속가능성·소재·디자인 해결형",
        "stage": "stage1"
      }
    ],
    "센서": [
      {
        "seedId": "RPT-001",
        "seedName": "시스템·데이터 기반 위험 예측형",
        "stage": "stage1"
      }
    ],
    "소비자": [
      {
        "seedId": "RPT-002",
        "seedName": "지속가능성·소재·디자인 해결형",
        "stage": "stage1"
      }
    ],
    "소재 구조": [
      {
        "seedId": "RPT-006",
        "seedName": "바이오매스·전기화학 촉매 전환형",
        "stage": "stage2"
      }
    ],
    "소재 물성": [
      {
        "seedId": "RPT-002",
        "seedName": "지속가능성·소재·디자인 해결형",
        "stage": "stage1"
      }
    ],
    "스마트시티": [
      {
        "seedId": "RPT-005",
        "seedName": "공간 데이터·도시 최적화 모델링형",
        "stage": "stage1"
      }
    ],
    "시나리오": [
      {
        "seedId": "RPT-003",
        "seedName": "지구시스템·기후 데이터 해석형",
        "stage": "stage1"
      }
    ],
    "시냅스": [
      {
        "seedId": "RPT-007",
        "seedName": "분자기전·질병 메커니즘 해석형",
        "stage": "stage2"
      }
    ],
    "시스템 비교": [
      {
        "seedId": "RPT-008",
        "seedName": "핵에너지·물리 원리 기반 시스템 안전형",
        "stage": "stage2"
      }
    ],
    "시스템 설계": [
      {
        "seedId": "RPT-001",
        "seedName": "시스템·데이터 기반 위험 예측형",
        "stage": "stage1"
      }
    ],
    "안전 관리": [
      {
        "seedId": "RPT-001",
        "seedName": "시스템·데이터 기반 위험 예측형",
        "stage": "stage1"
      }
    ],
    "안전 설계": [
      {
        "seedId": "RPT-008",
        "seedName": "핵에너지·물리 원리 기반 시스템 안전형",
        "stage": "stage2"
      }
    ],
    "약물 작용": [
      {
        "seedId": "RPT-007",
        "seedName": "분자기전·질병 메커니즘 해석형",
        "stage": "stage2"
      }
    ],
    "업사이클링": [
      {
        "seedId": "RPT-002",
        "seedName": "지속가능성·소재·디자인 해결형",
        "stage": "stage1"
      }
    ],
    "에너지 전환": [
      {
        "seedId": "RPT-008",
        "seedName": "핵에너지·물리 원리 기반 시스템 안전형",
        "stage": "stage2"
      }
    ],
    "연쇄반응": [
      {
        "seedId": "RPT-008",
        "seedName": "핵에너지·물리 원리 기반 시스템 안전형",
        "stage": "stage2"
      }
    ],
    "위기개입": [
      {
        "seedId": "RPT-009",
        "seedName": "의료사회복지·위기개입 정책 설계형",
        "stage": "stage2"
      }
    ],
    "위험 예측": [
      {
        "seedId": "RPT-001",
        "seedName": "시스템·데이터 기반 위험 예측형",
        "stage": "stage1"
      }
    ],
    "유전자": [
      {
        "seedId": "RPT-007",
        "seedName": "분자기전·질병 메커니즘 해석형",
        "stage": "stage2"
      }
    ],
    "의료윤리": [
      {
        "seedId": "RPT-009",
        "seedName": "의료사회복지·위기개입 정책 설계형",
        "stage": "stage2"
      }
    ],
    "의생명": [
      {
        "seedId": "RPT-007",
        "seedName": "분자기전·질병 메커니즘 해석형",
        "stage": "stage2"
      }
    ],
    "이해관계자": [
      {
        "seedId": "RPT-004",
        "seedName": "사회문제·정책 거버넌스 평가형",
        "stage": "stage1"
      }
    ],
    "임계": [
      {
        "seedId": "RPT-008",
        "seedName": "핵에너지·물리 원리 기반 시스템 안전형",
        "stage": "stage2"
      }
    ],
    "입지": [
      {
        "seedId": "RPT-005",
        "seedName": "공간 데이터·도시 최적화 모델링형",
        "stage": "stage1"
      }
    ],
    "자동화": [
      {
        "seedId": "RPT-001",
        "seedName": "시스템·데이터 기반 위험 예측형",
        "stage": "stage1"
      }
    ],
    "자료 해석": [
      {
        "seedId": "RPT-003",
        "seedName": "지구시스템·기후 데이터 해석형",
        "stage": "stage1"
      }
    ],
    "자원순환": [
      {
        "seedId": "RPT-002",
        "seedName": "지속가능성·소재·디자인 해결형",
        "stage": "stage1"
      }
    ],
    "장기 데이터": [
      {
        "seedId": "RPT-003",
        "seedName": "지구시스템·기후 데이터 해석형",
        "stage": "stage1"
      }
    ],
    "전기화학": [
      {
        "seedId": "RPT-006",
        "seedName": "바이오매스·전기화학 촉매 전환형",
        "stage": "stage2"
      }
    ],
    "접근성": [
      {
        "seedId": "RPT-005",
        "seedName": "공간 데이터·도시 최적화 모델링형",
        "stage": "stage1"
      }
    ],
    "정책": [
      {
        "seedId": "RPT-004",
        "seedName": "사회문제·정책 거버넌스 평가형",
        "stage": "stage1"
      }
    ],
    "정책 설계": [
      {
        "seedId": "RPT-009",
        "seedName": "의료사회복지·위기개입 정책 설계형",
        "stage": "stage2"
      }
    ],
    "정치갈등": [
      {
        "seedId": "RPT-010",
        "seedName": "미시-거시 구조 비교·정치사회 데이터 분석형",
        "stage": "stage2"
      }
    ],
    "제도": [
      {
        "seedId": "RPT-004",
        "seedName": "사회문제·정책 거버넌스 평가형",
        "stage": "stage1"
      }
    ],
    "지방": [
      {
        "seedId": "RPT-004",
        "seedName": "사회문제·정책 거버넌스 평가형",
        "stage": "stage1"
      }
    ],
    "지속가능성": [
      {
        "seedId": "RPT-002",
        "seedName": "지속가능성·소재·디자인 해결형",
        "stage": "stage1"
      },
      {
        "seedId": "RPT-006",
        "seedName": "바이오매스·전기화학 촉매 전환형",
        "stage": "stage2"
      }
    ],
    "지역 영향": [
      {
        "seedId": "RPT-003",
        "seedName": "지구시스템·기후 데이터 해석형",
        "stage": "stage1"
      }
    ],
    "질병 원리": [
      {
        "seedId": "RPT-007",
        "seedName": "분자기전·질병 메커니즘 해석형",
        "stage": "stage2"
      }
    ],
    "집단 갈등": [
      {
        "seedId": "RPT-010",
        "seedName": "미시-거시 구조 비교·정치사회 데이터 분석형",
        "stage": "stage2"
      }
    ],
    "촉매": [
      {
        "seedId": "RPT-006",
        "seedName": "바이오매스·전기화학 촉매 전환형",
        "stage": "stage2"
      }
    ],
    "최적화": [
      {
        "seedId": "RPT-005",
        "seedName": "공간 데이터·도시 최적화 모델링형",
        "stage": "stage1"
      }
    ],
    "치료 후보": [
      {
        "seedId": "RPT-007",
        "seedName": "분자기전·질병 메커니즘 해석형",
        "stage": "stage2"
      }
    ],
    "친환경 공정": [
      {
        "seedId": "RPT-006",
        "seedName": "바이오매스·전기화학 촉매 전환형",
        "stage": "stage2"
      }
    ],
    "폐자원": [
      {
        "seedId": "RPT-006",
        "seedName": "바이오매스·전기화학 촉매 전환형",
        "stage": "stage2"
      }
    ],
    "프레이밍": [
      {
        "seedId": "RPT-010",
        "seedName": "미시-거시 구조 비교·정치사회 데이터 분석형",
        "stage": "stage2"
      }
    ],
    "피동안전": [
      {
        "seedId": "RPT-008",
        "seedName": "핵에너지·물리 원리 기반 시스템 안전형",
        "stage": "stage2"
      }
    ],
    "해양 순환": [
      {
        "seedId": "RPT-003",
        "seedName": "지구시스템·기후 데이터 해석형",
        "stage": "stage1"
      }
    ],
    "핵분열": [
      {
        "seedId": "RPT-008",
        "seedName": "핵에너지·물리 원리 기반 시스템 안전형",
        "stage": "stage2"
      }
    ],
    "형평성": [
      {
        "seedId": "RPT-005",
        "seedName": "공간 데이터·도시 최적화 모델링형",
        "stage": "stage1"
      }
    ],
    "환경 변화": [
      {
        "seedId": "RPT-003",
        "seedName": "지구시스템·기후 데이터 해석형",
        "stage": "stage1"
      }
    ],
    "환경 영향": [
      {
        "seedId": "RPT-002",
        "seedName": "지속가능성·소재·디자인 해결형",
        "stage": "stage1"
      }
    ]
  },
  "byFusionType": {
    "공간 구조 + 수학 모델 + 데이터 시각화 + 도시 문제 해결": [
      {
        "seedId": "RPT-005",
        "seedName": "공간 데이터·도시 최적화 모델링형",
        "stage": "stage1"
      }
    ],
    "교과 원리 + 위험 변수 분해 + 센서/데이터 + 예방 시스템 설계": [
      {
        "seedId": "RPT-001",
        "seedName": "시스템·데이터 기반 위험 예측형",
        "stage": "stage1"
      }
    ],
    "물리 원리 + 에너지 전환 + 제어 변수 + 안전 시스템 설계": [
      {
        "seedId": "RPT-008",
        "seedName": "핵에너지·물리 원리 기반 시스템 안전형",
        "stage": "stage2"
      }
    ],
    "사회 문제 + 제도/정책 + 이해관계자 + 비용·편익 또는 효과 평가": [
      {
        "seedId": "RPT-004",
        "seedName": "사회문제·정책 거버넌스 평가형",
        "stage": "stage1"
      }
    ],
    "사회문화 이론 + 정치 갈등 구조 + 통계 지표 + 프레이밍 분석": [
      {
        "seedId": "RPT-010",
        "seedName": "미시-거시 구조 비교·정치사회 데이터 분석형",
        "stage": "stage2"
      }
    ],
    "사회복지 이론 + 경제 지표 + 윤리·상담 + 공공 서비스 설계": [
      {
        "seedId": "RPT-009",
        "seedName": "의료사회복지·위기개입 정책 설계형",
        "stage": "stage2"
      }
    ],
    "생명과학 개념 + 분자 상호작용 + 신경 회로 균형 + 치료 가능성 검토": [
      {
        "seedId": "RPT-007",
        "seedName": "분자기전·질병 메커니즘 해석형",
        "stage": "stage2"
      }
    ],
    "소재 물성 + 자원순환 + 디자인/소비자 행동 + 환경 영향": [
      {
        "seedId": "RPT-002",
        "seedName": "지속가능성·소재·디자인 해결형",
        "stage": "stage1"
      }
    ],
    "지구과학 원리 + 기후 시나리오 + 지역 영향 + 자료 해석": [
      {
        "seedId": "RPT-003",
        "seedName": "지구시스템·기후 데이터 해석형",
        "stage": "stage1"
      }
    ],
    "화학 원리 + 소재 표면 구조 + 전기화학 반응 + 친환경 생산 공정": [
      {
        "seedId": "RPT-006",
        "seedName": "바이오매스·전기화학 촉매 전환형",
        "stage": "stage2"
      }
    ]
  }
}