[
  {
    "major_id": "major_고고학과",
    "display_name": "고고학과",
    "bridge_key": "고고",
    "bridge_confidence": "high",
    "book_candidates": [
      {
        "book_id": "book_012",
        "title": "그리스 비극 걸작선"
      },
      {
        "book_id": "book_033",
        "title": "성의 역사 1"
      },
      {
        "book_id": "book_034",
        "title": "성호사설"
      }
    ]
  },
  {
    "major_id": "major_국어국문학과",
    "display_name": "국어국문학과",
    "bridge_key": "국어국문",
    "bridge_confidence": "high",
    "book_candidates": [
      {
        "book_id": "book_galmaegi",
        "title": "갈매기"
      },
      {
        "book_id": "book_004",
        "title": "겐지 이야기"
      },
      {
        "book_id": "book_006",
        "title": "고리오 영감"
      },
      {
        "book_id": "book_007",
        "title": "고향"
      },
      {
        "book_id": "book_009",
        "title": "광장"
      },
      {
        "book_id": "book_012",
        "title": "그리스 비극 걸작선"
      },
      {
        "book_id": "book_demian",
        "title": "데미안"
      },
      {
        "book_id": "book_020",
        "title": "마음"
      },
      {
        "book_id": "book_022",
        "title": "무정"
      },
      {
        "book_id": "book_026",
        "title": "백범일지"
      }
    ]
  },
  {
    "major_id": "major_노어노문학과",
    "display_name": "노어노문학과",
    "bridge_key": "노어노문",
    "bridge_confidence": "high",
    "book_candidates": [
      {
        "book_id": "book_galmaegi",
        "title": "갈매기"
      },
      {
        "book_id": "book_068",
        "title": "카라마조프가의 형제들"
      }
    ]
  },
  {
    "major_id": "major_독어독문학과",
    "display_name": "독어독문학과",
    "bridge_key": "독어독문",
    "bridge_confidence": "high",
    "book_candidates": [
      {
        "book_id": "book_027",
        "title": "변신"
      },
      {
        "book_id": "book_037",
        "title": "시학"
      },
      {
        "book_id": "book_065",
        "title": "짜라투스트라는 이렇게 말했다"
      }
    ]
  },
  {
    "major_id": "major_문예창작학과",
    "display_name": "문예창작학과",
    "bridge_key": "문예창작",
    "bridge_confidence": "high",
    "book_candidates": [
      {
        "book_id": "book_037",
        "title": "시학"
      },
      {
        "book_id": "book_040",
        "title": "아라비안 나이트"
      },
      {
        "book_id": "book_059",
        "title": "젊은 예술가의 초상"
      },
      {
        "book_id": "book_061",
        "title": "정지용전집"
      },
      {
        "book_id": "book_066",
        "title": "천변풍경"
      },
      {
        "book_id": "book_068",
        "title": "카라마조프가의 형제들"
      }
    ]
  },
  {
    "major_id": "major_문화인류학과",
    "display_name": "문화인류학과",
    "bridge_key": "문화인류",
    "bridge_confidence": "high",
    "book_candidates": [
      {
        "book_id": "book_004",
        "title": "겐지 이야기"
      },
      {
        "book_id": "book_011",
        "title": "국화와 칼"
      },
      {
        "book_id": "book_018",
        "title": "동방견문록"
      },
      {
        "book_id": "book_029",
        "title": "빌러비드"
      },
      {
        "book_id": "book_031",
        "title": "삼대"
      },
      {
        "book_id": "book_033",
        "title": "성의 역사 1"
      },
      {
        "book_id": "book_036",
        "title": "슬픈 열대"
      },
      {
        "book_id": "book_043",
        "title": "어둠의 심장"
      },
      {
        "book_id": "book_044",
        "title": "역사"
      },
      {
        "book_id": "book_047",
        "title": "오리엔탈리즘"
      }
    ]
  },
  {
    "major_id": "major_미학과",
    "display_name": "미학과",
    "bridge_key": "고고미술사",
    "bridge_confidence": "medium",
    "book_candidates": [
      {
        "book_id": "book_018",
        "title": "동방견문록"
      }
    ]
  },
  {
    "major_id": "major_불어불문학과",
    "display_name": "불어불문학과",
    "bridge_key": "불문",
    "bridge_confidence": "medium",
    "book_candidates": [
      {
        "book_id": "book_057",
        "title": "잃어버린 시간을 찾아서"
      }
    ]
  },
  {
    "major_id": "major_사학과",
    "display_name": "사학과",
    "bridge_key": "경제정치사회융합",
    "bridge_confidence": "medium",
    "book_candidates": [
      {
        "book_id": "book_062",
        "title": "제국의 시대"
      }
    ]
  },
  {
    "major_id": "major_신학과",
    "display_name": "신학과",
    "bridge_key": "신문방송하과심리하과인류하과철",
    "bridge_confidence": "medium",
    "book_candidates": [
      {
        "book_id": "book_demian",
        "title": "데미안"
      }
    ]
  },
  {
    "major_id": "major_언어학과",
    "display_name": "언어학과",
    "bridge_key": "언어",
    "bridge_confidence": "high",
    "book_candidates": [
      {
        "book_id": "book_035",
        "title": "수호전"
      }
    ]
  },
  {
    "major_id": "major_영어영문학과",
    "display_name": "영어영문학과",
    "bridge_key": "영어영문",
    "bridge_confidence": "high",
    "book_candidates": [
      {
        "book_id": "book_029",
        "title": "빌러비드"
      },
      {
        "book_id": "book_039",
        "title": "실낙원"
      },
      {
        "book_id": "book_042",
        "title": "앵무새 죽이기"
      },
      {
        "book_id": "book_043",
        "title": "어둠의 심장"
      },
      {
        "book_id": "book_054",
        "title": "이상한 나라의 앨리스"
      },
      {
        "book_id": "book_059",
        "title": "젊은 예술가의 초상"
      },
      {
        "book_id": "book_064",
        "title": "죽은 시인의 사회"
      }
    ]
  },
  {
    "major_id": "major_일어일문학과",
    "display_name": "일어일문학과",
    "bridge_key": "일어일문",
    "bridge_confidence": "high",
    "book_candidates": [
      {
        "book_id": "book_004",
        "title": "겐지 이야기"
      },
      {
        "book_id": "book_020",
        "title": "마음"
      }
    ]
  },
  {
    "major_id": "major_중어중문학과",
    "display_name": "중어중문학과",
    "bridge_key": "중어중문",
    "bridge_confidence": "high",
    "book_candidates": [
      {
        "book_id": "book_035",
        "title": "수호전"
      }
    ]
  },
  {
    "major_id": "major_철학과",
    "display_name": "철학과",
    "bridge_key": "신문방송하과심리하과인류하과철",
    "bridge_confidence": "medium",
    "book_candidates": [
      {
        "book_id": "book_demian",
        "title": "데미안"
      }
    ]
  },
  {
    "major_id": "major_한문학과",
    "display_name": "한문학과",
    "bridge_key": "한문",
    "bridge_confidence": "high",
    "book_candidates": [
      {
        "book_id": "book_021",
        "title": "맹자"
      },
      {
        "book_id": "book_034",
        "title": "성호사설"
      },
      {
        "book_id": "book_041",
        "title": "아함경"
      },
      {
        "book_id": "book_056",
        "title": "인물로 읽는 장자"
      }
    ]
  },
  {
    "major_id": "major_경영정보학과",
    "display_name": "경영정보학과",
    "bridge_key": "경영",
    "bridge_confidence": "medium",
    "book_candidates": [
      {
        "book_id": "book_gyeongyeonghak",
        "title": "경영학 콘서트"
      },
      {
        "book_id": "book_021",
        "title": "맹자"
      },
      {
        "book_id": "book_022",
        "title": "무정"
      }
    ]
  },
  {
    "major_id": "major_경영학과",
    "display_name": "경영학과",
    "bridge_key": "경영",
    "bridge_confidence": "high",
    "book_candidates": [
      {
        "book_id": "book_gyeongyeonghak",
        "title": "경영학 콘서트"
      },
      {
        "book_id": "book_021",
        "title": "맹자"
      },
      {
        "book_id": "book_022",
        "title": "무정"
      }
    ]
  },
  {
    "major_id": "major_경제학과",
    "display_name": "경제학과",
    "bridge_key": "경제",
    "bridge_confidence": "high",
    "book_candidates": [
      {
        "book_id": "book_008",
        "title": "공정하다는 착각"
      },
      {
        "book_id": "book_017",
        "title": "돈으로 살 수 없는 것들"
      },
      {
        "book_id": "book_023",
        "title": "문학과 예술의 사회사"
      },
      {
        "book_id": "book_045",
        "title": "역사와 계급의식"
      },
      {
        "book_id": "book_048",
        "title": "왜 세계의 절반은 굶주리는가"
      },
      {
        "book_id": "book_054",
        "title": "이상한 나라의 앨리스"
      },
      {
        "book_id": "book_062",
        "title": "제국의 시대"
      }
    ]
  },
  {
    "major_id": "major_경찰행정학과",
    "display_name": "경찰행정학과",
    "bridge_key": "행정",
    "bridge_confidence": "medium",
    "book_candidates": [
      {
        "book_id": "book_1984",
        "title": "1984"
      },
      {
        "book_id": "book_010",
        "title": "국가"
      },
      {
        "book_id": "book_013",
        "title": "난장이가 쏘아올린 작은 공"
      },
      {
        "book_id": "book_014",
        "title": "누구나 한번쯤 읽어야 할 목민심서"
      },
      {
        "book_id": "book_026",
        "title": "백범일지"
      },
      {
        "book_id": "book_032",
        "title": "서유견문"
      },
      {
        "book_id": "book_043",
        "title": "어둠의 심장"
      },
      {
        "book_id": "book_044",
        "title": "역사"
      },
      {
        "book_id": "book_055",
        "title": "인간 문제"
      }
    ]
  },
  {
    "major_id": "major_관광경영학과",
    "display_name": "관광경영학과",
    "bridge_key": "관광경영",
    "bridge_confidence": "high",
    "book_candidates": [
      {
        "book_id": "book_011",
        "title": "국화와 칼"
      }
    ]
  },
  {
    "major_id": "major_광고홍보학과",
    "display_name": "광고홍보학과",
    "bridge_key": "광고홍보",
    "bridge_confidence": "high",
    "book_candidates": [
      {
        "book_id": "book_024",
        "title": "미디어의 이해"
      }
    ]
  },
  {
    "major_id": "major_국제통상학과",
    "display_name": "국제통상학과",
    "bridge_key": "국제",
    "bridge_confidence": "medium",
    "book_candidates": [
      {
        "book_id": "book_011",
        "title": "국화와 칼"
      },
      {
        "book_id": "book_018",
        "title": "동방견문록"
      },
      {
        "book_id": "book_032",
        "title": "서유견문"
      },
      {
        "book_id": "book_047",
        "title": "오리엔탈리즘"
      },
      {
        "book_id": "book_048",
        "title": "왜 세계의 절반은 굶주리는가"
      },
      {
        "book_id": "book_062",
        "title": "제국의 시대"
      }
    ]
  },
  {
    "major_id": "major_국제학부",
    "display_name": "국제학부",
    "bridge_key": "국제",
    "bridge_confidence": "high",
    "book_candidates": [
      {
        "book_id": "book_011",
        "title": "국화와 칼"
      },
      {
        "book_id": "book_018",
        "title": "동방견문록"
      },
      {
        "book_id": "book_032",
        "title": "서유견문"
      },
      {
        "book_id": "book_047",
        "title": "오리엔탈리즘"
      },
      {
        "book_id": "book_048",
        "title": "왜 세계의 절반은 굶주리는가"
      },
      {
        "book_id": "book_062",
        "title": "제국의 시대"
      }
    ]
  },
  {
    "major_id": "major_글로벌경영학과",
    "display_name": "글로벌경영학과",
    "bridge_key": "경영",
    "bridge_confidence": "medium",
    "book_candidates": [
      {
        "book_id": "book_gyeongyeonghak",
        "title": "경영학 콘서트"
      },
      {
        "book_id": "book_021",
        "title": "맹자"
      },
      {
        "book_id": "book_022",
        "title": "무정"
      }
    ]
  },
  {
    "major_id": "major_농업경제학과",
    "display_name": "농업경제학과",
    "bridge_key": "경제",
    "bridge_confidence": "medium",
    "book_candidates": [
      {
        "book_id": "book_008",
        "title": "공정하다는 착각"
      },
      {
        "book_id": "book_017",
        "title": "돈으로 살 수 없는 것들"
      },
      {
        "book_id": "book_023",
        "title": "문학과 예술의 사회사"
      },
      {
        "book_id": "book_045",
        "title": "역사와 계급의식"
      },
      {
        "book_id": "book_048",
        "title": "왜 세계의 절반은 굶주리는가"
      },
      {
        "book_id": "book_054",
        "title": "이상한 나라의 앨리스"
      },
      {
        "book_id": "book_062",
        "title": "제국의 시대"
      }
    ]
  },
  {
    "major_id": "major_도시행정학과",
    "display_name": "도시행정학과",
    "bridge_key": "행정",
    "bridge_confidence": "medium",
    "book_candidates": [
      {
        "book_id": "book_1984",
        "title": "1984"
      },
      {
        "book_id": "book_010",
        "title": "국가"
      },
      {
        "book_id": "book_013",
        "title": "난장이가 쏘아올린 작은 공"
      },
      {
        "book_id": "book_014",
        "title": "누구나 한번쯤 읽어야 할 목민심서"
      },
      {
        "book_id": "book_026",
        "title": "백범일지"
      },
      {
        "book_id": "book_032",
        "title": "서유견문"
      },
      {
        "book_id": "book_043",
        "title": "어둠의 심장"
      },
      {
        "book_id": "book_044",
        "title": "역사"
      },
      {
        "book_id": "book_055",
        "title": "인간 문제"
      }
    ]
  },
  {
    "major_id": "major_무역학과",
    "display_name": "무역학과",
    "bridge_key": "무역",
    "bridge_confidence": "high",
    "book_candidates": [
      {
        "book_id": "book_017",
        "title": "돈으로 살 수 없는 것들"
      }
    ]
  },
  {
    "major_id": "major_문화콘텐츠학과",
    "display_name": "문화콘텐츠학과",
    "bridge_key": "문화콘텐츠",
    "bridge_confidence": "high",
    "book_candidates": [
      {
        "book_id": "book_022",
        "title": "무정"
      },
      {
        "book_id": "book_023",
        "title": "문학과 예술의 사회사"
      },
      {
        "book_id": "book_027",
        "title": "변신"
      },
      {
        "book_id": "book_036",
        "title": "슬픈 열대"
      },
      {
        "book_id": "book_037",
        "title": "시학"
      }
    ]
  },
  {
    "major_id": "major_미디어커뮤니케이션학과",
    "display_name": "미디어커뮤니케이션학과",
    "bridge_key": "미디어커뮤니케이션",
    "bridge_confidence": "high",
    "book_candidates": [
      {
        "book_id": "book_1984",
        "title": "1984"
      },
      {
        "book_id": "book_024",
        "title": "미디어의 이해"
      },
      {
        "book_id": "book_040",
        "title": "아라비안 나이트"
      },
      {
        "book_id": "book_047",
        "title": "오리엔탈리즘"
      },
      {
        "book_id": "book_066",
        "title": "천변풍경"
      }
    ]
  },
  {
    "major_id": "major_부동산학과",
    "display_name": "부동산학과",
    "bridge_key": "도시계뢰부동산",
    "bridge_confidence": "medium",
    "book_candidates": [
      {
        "book_id": "book_013",
        "title": "난장이가 쏘아올린 작은 공"
      }
    ]
  },
  {
    "major_id": "major_사회복지학과",
    "display_name": "사회복지학과",
    "bridge_key": "사회복지",
    "bridge_confidence": "high",
    "book_candidates": [
      {
        "book_id": "book_010",
        "title": "국가"
      },
      {
        "book_id": "book_019",
        "title": "동물 세포에는 세포벽이 없다"
      }
    ]
  },
  {
    "major_id": "major_사회학과",
    "display_name": "사회학과",
    "bridge_key": "사회",
    "bridge_confidence": "high",
    "book_candidates": [
      {
        "book_id": "book_1984",
        "title": "1984"
      },
      {
        "book_id": "book_006",
        "title": "고리오 영감"
      },
      {
        "book_id": "book_007",
        "title": "고향"
      },
      {
        "book_id": "book_008",
        "title": "공정하다는 착각"
      },
      {
        "book_id": "book_009",
        "title": "광장"
      },
      {
        "book_id": "book_013",
        "title": "난장이가 쏘아올린 작은 공"
      },
      {
        "book_id": "book_020",
        "title": "마음"
      },
      {
        "book_id": "book_023",
        "title": "문학과 예술의 사회사"
      },
      {
        "book_id": "book_030",
        "title": "사람아, 아 사람아!"
      },
      {
        "book_id": "book_031",
        "title": "삼대"
      }
    ]
  },
  {
    "major_id": "major_상담심리학과",
    "display_name": "상담심리학과",
    "bridge_key": "심리",
    "bridge_confidence": "medium",
    "book_candidates": [
      {
        "book_id": "book_galmaegi",
        "title": "갈매기"
      },
      {
        "book_id": "book_006",
        "title": "고리오 영감"
      },
      {
        "book_id": "book_010",
        "title": "국가"
      },
      {
        "book_id": "book_014",
        "title": "누구나 한번쯤 읽어야 할 목민심서"
      },
      {
        "book_id": "book_doctorsignal",
        "title": "닥터스 씽킹"
      },
      {
        "book_id": "book_demian",
        "title": "데미안"
      },
      {
        "book_id": "book_020",
        "title": "마음"
      },
      {
        "book_id": "book_027",
        "title": "변신"
      },
      {
        "book_id": "book_030",
        "title": "사람아, 아 사람아!"
      },
      {
        "book_id": "book_049",
        "title": "우리 시대의 영웅"
      }
    ]
  },
  {
    "major_id": "major_식품자원경제학과",
    "display_name": "식품자원경제학과",
    "bridge_key": "경제",
    "bridge_confidence": "medium",
    "book_candidates": [
      {
        "book_id": "book_008",
        "title": "공정하다는 착각"
      },
      {
        "book_id": "book_017",
        "title": "돈으로 살 수 없는 것들"
      },
      {
        "book_id": "book_023",
        "title": "문학과 예술의 사회사"
      },
      {
        "book_id": "book_045",
        "title": "역사와 계급의식"
      },
      {
        "book_id": "book_048",
        "title": "왜 세계의 절반은 굶주리는가"
      },
      {
        "book_id": "book_054",
        "title": "이상한 나라의 앨리스"
      },
      {
        "book_id": "book_062",
        "title": "제국의 시대"
      }
    ]
  },
  {
    "major_id": "major_신문방송학과",
    "display_name": "신문방송학과",
    "bridge_key": "신문방송하과심리하과인류하과철",
    "bridge_confidence": "medium",
    "book_candidates": [
      {
        "book_id": "book_demian",
        "title": "데미안"
      }
    ]
  },
  {
    "major_id": "major_심리학과",
    "display_name": "심리학과",
    "bridge_key": "심리",
    "bridge_confidence": "high",
    "book_candidates": [
      {
        "book_id": "book_galmaegi",
        "title": "갈매기"
      },
      {
        "book_id": "book_006",
        "title": "고리오 영감"
      },
      {
        "book_id": "book_010",
        "title": "국가"
      },
      {
        "book_id": "book_014",
        "title": "누구나 한번쯤 읽어야 할 목민심서"
      },
      {
        "book_id": "book_doctorsignal",
        "title": "닥터스 씽킹"
      },
      {
        "book_id": "book_demian",
        "title": "데미안"
      },
      {
        "book_id": "book_020",
        "title": "마음"
      },
      {
        "book_id": "book_027",
        "title": "변신"
      },
      {
        "book_id": "book_030",
        "title": "사람아, 아 사람아!"
      },
      {
        "book_id": "book_049",
        "title": "우리 시대의 영웅"
      }
    ]
  },
  {
    "major_id": "major_언론정보학과",
    "display_name": "언론정보학과",
    "bridge_key": "언론정보",
    "bridge_confidence": "high",
    "book_candidates": [
      {
        "book_id": "book_024",
        "title": "미디어의 이해"
      },
      {
        "book_id": "book_025",
        "title": "반지성주의"
      }
    ]
  },
  {
    "major_id": "major_응용통계학과",
    "display_name": "응용통계학과",
    "bridge_key": "통계",
    "bridge_confidence": "medium",
    "book_candidates": [
      {
        "book_id": "book_gyeongyeonghak",
        "title": "경영학 콘서트"
      }
    ]
  },
  {
    "major_id": "major_정치외교학과",
    "display_name": "정치외교학과",
    "bridge_key": "정치외교",
    "bridge_confidence": "high",
    "book_candidates": [
      {
        "book_id": "book_007",
        "title": "고향"
      },
      {
        "book_id": "book_008",
        "title": "공정하다는 착각"
      },
      {
        "book_id": "book_009",
        "title": "광장"
      },
      {
        "book_id": "book_010",
        "title": "국가"
      },
      {
        "book_id": "book_014",
        "title": "누구나 한번쯤 읽어야 할 목민심서"
      },
      {
        "book_id": "book_017",
        "title": "돈으로 살 수 없는 것들"
      },
      {
        "book_id": "book_025",
        "title": "반지성주의"
      },
      {
        "book_id": "book_026",
        "title": "백범일지"
      },
      {
        "book_id": "book_030",
        "title": "사람아, 아 사람아!"
      },
      {
        "book_id": "book_032",
        "title": "서유견문"
      }
    ]
  },
  {
    "major_id": "major_행정학과",
    "display_name": "행정학과",
    "bridge_key": "행정",
    "bridge_confidence": "high",
    "book_candidates": [
      {
        "book_id": "book_1984",
        "title": "1984"
      },
      {
        "book_id": "book_010",
        "title": "국가"
      },
      {
        "book_id": "book_013",
        "title": "난장이가 쏘아올린 작은 공"
      },
      {
        "book_id": "book_014",
        "title": "누구나 한번쯤 읽어야 할 목민심서"
      },
      {
        "book_id": "book_026",
        "title": "백범일지"
      },
      {
        "book_id": "book_032",
        "title": "서유견문"
      },
      {
        "book_id": "book_043",
        "title": "어둠의 심장"
      },
      {
        "book_id": "book_044",
        "title": "역사"
      },
      {
        "book_id": "book_055",
        "title": "인간 문제"
      }
    ]
  },
  {
    "major_id": "major_호텔경영학과",
    "display_name": "호텔경영학과",
    "bridge_key": "경영",
    "bridge_confidence": "medium",
    "book_candidates": [
      {
        "book_id": "book_gyeongyeonghak",
        "title": "경영학 콘서트"
      },
      {
        "book_id": "book_021",
        "title": "맹자"
      },
      {
        "book_id": "book_022",
        "title": "무정"
      }
    ]
  },
  {
    "major_id": "major_회계학과",
    "display_name": "회계학과",
    "bridge_key": "회계",
    "bridge_confidence": "high",
    "book_candidates": [
      {
        "book_id": "book_gyeongyeonghak",
        "title": "경영학 콘서트"
      }
    ]
  },
  {
    "major_id": "major_물리학과",
    "display_name": "물리학과",
    "bridge_key": "물리",
    "bridge_confidence": "high",
    "book_candidates": [
      {
        "book_id": "book_003",
        "title": "객관성의 칼날"
      },
      {
        "book_id": "book_028",
        "title": "부분과 전체"
      },
      {
        "book_id": "book_069",
        "title": "카오스"
      },
      {
        "book_id": "book_cosmos_intro",
        "title": "코스모스"
      }
    ]
  },
  {
    "major_id": "major_생명공학과",
    "display_name": "생명공학과",
    "bridge_key": "생명공",
    "bridge_confidence": "high",
    "book_candidates": [
      {
        "book_id": "book_019",
        "title": "동물 세포에는 세포벽이 없다"
      },
      {
        "book_id": "book_053",
        "title": "이기적 유전자"
      },
      {
        "book_id": "book_063",
        "title": "종의 기원"
      }
    ]
  },
  {
    "major_id": "major_생명과학과",
    "display_name": "생명과학과",
    "bridge_key": "생명과",
    "bridge_confidence": "high",
    "book_candidates": [
      {
        "book_id": "book_003",
        "title": "객관성의 칼날"
      },
      {
        "book_id": "book_doctorsignal",
        "title": "닥터스 씽킹"
      },
      {
        "book_id": "book_019",
        "title": "동물 세포에는 세포벽이 없다"
      },
      {
        "book_id": "book_053",
        "title": "이기적 유전자"
      },
      {
        "book_id": "book_063",
        "title": "종의 기원"
      }
    ]
  },
  {
    "major_id": "major_생물학과",
    "display_name": "생물학과",
    "bridge_key": "생물교육과",
    "bridge_confidence": "medium",
    "book_candidates": [
      {
        "book_id": "book_053",
        "title": "이기적 유전자"
      },
      {
        "book_id": "book_063",
        "title": "종의 기원"
      }
    ]
  },
  {
    "major_id": "major_수산생명의학과",
    "display_name": "수산생명의학과",
    "bridge_key": "의학",
    "bridge_confidence": "medium",
    "book_candidates": [
      {
        "book_id": "book_doctorsignal",
        "title": "닥터스 씽킹"
      },
      {
        "book_id": "book_019",
        "title": "동물 세포에는 세포벽이 없다"
      },
      {
        "book_id": "book_050",
        "title": "위대하고 위험한 약 이야기"
      },
      {
        "book_id": "book_052",
        "title": "의사와 수의사가 만나다"
      },
      {
        "book_id": "book_067",
        "title": "치과의사가 말하는 치과의사"
      }
    ]
  },
  {
    "major_id": "major_수학과",
    "display_name": "수학과",
    "bridge_key": "수의",
    "bridge_confidence": "medium",
    "book_candidates": [
      {
        "book_id": "book_019",
        "title": "동물 세포에는 세포벽이 없다"
      },
      {
        "book_id": "book_053",
        "title": "이기적 유전자"
      },
      {
        "book_id": "book_063",
        "title": "종의 기원"
      }
    ]
  },
  {
    "major_id": "major_천문우주학과",
    "display_name": "천문우주학과",
    "bridge_key": "천문",
    "bridge_confidence": "medium",
    "book_candidates": [
      {
        "book_id": "book_069",
        "title": "카오스"
      },
      {
        "book_id": "book_cosmos_intro",
        "title": "코스모스"
      }
    ]
  },
  {
    "major_id": "major_통계학과",
    "display_name": "통계학과",
    "bridge_key": "통계",
    "bridge_confidence": "high",
    "book_candidates": [
      {
        "book_id": "book_gyeongyeonghak",
        "title": "경영학 콘서트"
      }
    ]
  },
  {
    "major_id": "major_화학과",
    "display_name": "화학과",
    "bridge_key": "고고문화인류",
    "bridge_confidence": "medium",
    "book_candidates": [
      {
        "book_id": "book_012",
        "title": "그리스 비극 걸작선"
      }
    ]
  },
  {
    "major_id": "major_도시공학과",
    "display_name": "도시공학과",
    "bridge_key": "도시공",
    "bridge_confidence": "high",
    "book_candidates": [
      {
        "book_id": "book_013",
        "title": "난장이가 쏘아올린 작은 공"
      },
      {
        "book_id": "book_055",
        "title": "인간 문제"
      }
    ]
  },
  {
    "major_id": "major_산업경영공학과",
    "display_name": "산업경영공학과",
    "bridge_key": "경영",
    "bridge_confidence": "medium",
    "book_candidates": [
      {
        "book_id": "book_gyeongyeonghak",
        "title": "경영학 콘서트"
      },
      {
        "book_id": "book_021",
        "title": "맹자"
      },
      {
        "book_id": "book_022",
        "title": "무정"
      }
    ]
  },
  {
    "major_id": "major_산업공학과",
    "display_name": "산업공학과",
    "bridge_key": "산업공",
    "bridge_confidence": "high",
    "book_candidates": [
      {
        "book_id": "book_gyeongyeonghak",
        "title": "경영학 콘서트"
      }
    ]
  },
  {
    "major_id": "major_식품생명공학과",
    "display_name": "식품생명공학과",
    "bridge_key": "생명공",
    "bridge_confidence": "medium",
    "book_candidates": [
      {
        "book_id": "book_019",
        "title": "동물 세포에는 세포벽이 없다"
      },
      {
        "book_id": "book_053",
        "title": "이기적 유전자"
      },
      {
        "book_id": "book_063",
        "title": "종의 기원"
      }
    ]
  },
  {
    "major_id": "major_컴퓨터공학과",
    "display_name": "컴퓨터공학과",
    "bridge_key": "컴퓨터공",
    "bridge_confidence": "high",
    "book_candidates": [
      {
        "book_id": "book_1984",
        "title": "1984"
      },
      {
        "book_id": "book_024",
        "title": "미디어의 이해"
      }
    ]
  },
  {
    "major_id": "major_화공생명공학과",
    "display_name": "화공생명공학과",
    "bridge_key": "생명공",
    "bridge_confidence": "medium",
    "book_candidates": [
      {
        "book_id": "book_019",
        "title": "동물 세포에는 세포벽이 없다"
      },
      {
        "book_id": "book_053",
        "title": "이기적 유전자"
      },
      {
        "book_id": "book_063",
        "title": "종의 기원"
      }
    ]
  },
  {
    "major_id": "major_간호학과",
    "display_name": "간호학과",
    "bridge_key": "간호",
    "bridge_confidence": "high",
    "book_candidates": [
      {
        "book_id": "book_doctorsignal",
        "title": "닥터스 씽킹"
      },
      {
        "book_id": "book_038",
        "title": "신약의 탄생"
      },
      {
        "book_id": "book_050",
        "title": "위대하고 위험한 약 이야기"
      },
      {
        "book_id": "book_052",
        "title": "의사와 수의사가 만나다"
      },
      {
        "book_id": "book_067",
        "title": "치과의사가 말하는 치과의사"
      }
    ]
  },
  {
    "major_id": "major_물리치료학과",
    "display_name": "물리치료학과",
    "bridge_key": "물리",
    "bridge_confidence": "medium",
    "book_candidates": [
      {
        "book_id": "book_003",
        "title": "객관성의 칼날"
      },
      {
        "book_id": "book_028",
        "title": "부분과 전체"
      },
      {
        "book_id": "book_069",
        "title": "카오스"
      },
      {
        "book_id": "book_cosmos_intro",
        "title": "코스모스"
      }
    ]
  },
  {
    "major_id": "major_수의예과",
    "display_name": "수의예과",
    "bridge_key": "수의",
    "bridge_confidence": "high",
    "book_candidates": [
      {
        "book_id": "book_019",
        "title": "동물 세포에는 세포벽이 없다"
      },
      {
        "book_id": "book_053",
        "title": "이기적 유전자"
      },
      {
        "book_id": "book_063",
        "title": "종의 기원"
      }
    ]
  },
  {
    "major_id": "major_언어치료학과",
    "display_name": "언어치료학과",
    "bridge_key": "언어",
    "bridge_confidence": "medium",
    "book_candidates": [
      {
        "book_id": "book_035",
        "title": "수호전"
      }
    ]
  },
  {
    "major_id": "major_의예과",
    "display_name": "의예과",
    "bridge_key": "수의",
    "bridge_confidence": "medium",
    "book_candidates": [
      {
        "book_id": "book_019",
        "title": "동물 세포에는 세포벽이 없다"
      },
      {
        "book_id": "book_053",
        "title": "이기적 유전자"
      },
      {
        "book_id": "book_063",
        "title": "종의 기원"
      }
    ]
  },
  {
    "major_id": "major_치기공학과",
    "display_name": "치기공학과",
    "bridge_key": "치기공",
    "bridge_confidence": "high",
    "book_candidates": [
      {
        "book_id": "book_067",
        "title": "치과의사가 말하는 치과의사"
      }
    ]
  },
  {
    "major_id": "major_치의예과",
    "display_name": "치의예과",
    "bridge_key": "치의학",
    "bridge_confidence": "medium",
    "book_candidates": [
      {
        "book_id": "book_050",
        "title": "위대하고 위험한 약 이야기"
      },
      {
        "book_id": "book_067",
        "title": "치과의사가 말하는 치과의사"
      }
    ]
  },
  {
    "major_id": "major_미술학과",
    "display_name": "미술학과",
    "bridge_key": "고고미술사",
    "bridge_confidence": "medium",
    "book_candidates": [
      {
        "book_id": "book_018",
        "title": "동방견문록"
      }
    ]
  },
  {
    "major_id": "major_사회체육학과",
    "display_name": "사회체육학과",
    "bridge_key": "사회",
    "bridge_confidence": "medium",
    "book_candidates": [
      {
        "book_id": "book_1984",
        "title": "1984"
      },
      {
        "book_id": "book_006",
        "title": "고리오 영감"
      },
      {
        "book_id": "book_007",
        "title": "고향"
      },
      {
        "book_id": "book_008",
        "title": "공정하다는 착각"
      },
      {
        "book_id": "book_009",
        "title": "광장"
      },
      {
        "book_id": "book_013",
        "title": "난장이가 쏘아올린 작은 공"
      },
      {
        "book_id": "book_020",
        "title": "마음"
      },
      {
        "book_id": "book_023",
        "title": "문학과 예술의 사회사"
      },
      {
        "book_id": "book_030",
        "title": "사람아, 아 사람아!"
      },
      {
        "book_id": "book_031",
        "title": "삼대"
      }
    ]
  },
  {
    "major_id": "major_스포츠의학과",
    "display_name": "스포츠의학과",
    "bridge_key": "의학",
    "bridge_confidence": "medium",
    "book_candidates": [
      {
        "book_id": "book_doctorsignal",
        "title": "닥터스 씽킹"
      },
      {
        "book_id": "book_019",
        "title": "동물 세포에는 세포벽이 없다"
      },
      {
        "book_id": "book_050",
        "title": "위대하고 위험한 약 이야기"
      },
      {
        "book_id": "book_052",
        "title": "의사와 수의사가 만나다"
      },
      {
        "book_id": "book_067",
        "title": "치과의사가 말하는 치과의사"
      }
    ]
  },
  {
    "major_id": "major_연극영화학과",
    "display_name": "연극영화학과",
    "bridge_key": "연극영화과",
    "bridge_confidence": "medium",
    "book_candidates": [
      {
        "book_id": "book_galmaegi",
        "title": "갈매기"
      },
      {
        "book_id": "book_012",
        "title": "그리스 비극 걸작선"
      }
    ]
  },
  {
    "major_id": "major_조형예술학과",
    "display_name": "조형예술학과",
    "bridge_key": "예술",
    "bridge_confidence": "medium",
    "book_candidates": [
      {
        "book_id": "book_059",
        "title": "젊은 예술가의 초상"
      }
    ]
  },
  {
    "major_id": "major_가정교육과",
    "display_name": "가정교육과",
    "bridge_key": "교육",
    "bridge_confidence": "medium",
    "book_candidates": [
      {
        "book_id": "book_008",
        "title": "공정하다는 착각"
      },
      {
        "book_id": "book_demian",
        "title": "데미안"
      },
      {
        "book_id": "book_022",
        "title": "무정"
      },
      {
        "book_id": "book_024",
        "title": "미디어의 이해"
      },
      {
        "book_id": "book_025",
        "title": "반지성주의"
      },
      {
        "book_id": "book_026",
        "title": "백범일지"
      },
      {
        "book_id": "book_032",
        "title": "서유견문"
      },
      {
        "book_id": "book_058",
        "title": "자유론"
      },
      {
        "book_id": "book_060",
        "title": "정신현상학"
      },
      {
        "book_id": "book_064",
        "title": "죽은 시인의 사회"
      }
    ]
  },
  {
    "major_id": "major_과학교육과",
    "display_name": "과학교육과",
    "bridge_key": "과학교육과",
    "bridge_confidence": "high",
    "book_candidates": [
      {
        "book_id": "book_003",
        "title": "객관성의 칼날"
      },
      {
        "book_id": "book_028",
        "title": "부분과 전체"
      }
    ]
  },
  {
    "major_id": "major_교육공학과",
    "display_name": "교육공학과",
    "bridge_key": "교육",
    "bridge_confidence": "medium",
    "book_candidates": [
      {
        "book_id": "book_008",
        "title": "공정하다는 착각"
      },
      {
        "book_id": "book_demian",
        "title": "데미안"
      },
      {
        "book_id": "book_022",
        "title": "무정"
      },
      {
        "book_id": "book_024",
        "title": "미디어의 이해"
      },
      {
        "book_id": "book_025",
        "title": "반지성주의"
      },
      {
        "book_id": "book_026",
        "title": "백범일지"
      },
      {
        "book_id": "book_032",
        "title": "서유견문"
      },
      {
        "book_id": "book_058",
        "title": "자유론"
      },
      {
        "book_id": "book_060",
        "title": "정신현상학"
      },
      {
        "book_id": "book_064",
        "title": "죽은 시인의 사회"
      }
    ]
  },
  {
    "major_id": "major_교육학과",
    "display_name": "교육학과",
    "bridge_key": "교육",
    "bridge_confidence": "high",
    "book_candidates": [
      {
        "book_id": "book_008",
        "title": "공정하다는 착각"
      },
      {
        "book_id": "book_demian",
        "title": "데미안"
      },
      {
        "book_id": "book_022",
        "title": "무정"
      },
      {
        "book_id": "book_024",
        "title": "미디어의 이해"
      },
      {
        "book_id": "book_025",
        "title": "반지성주의"
      },
      {
        "book_id": "book_026",
        "title": "백범일지"
      },
      {
        "book_id": "book_032",
        "title": "서유견문"
      },
      {
        "book_id": "book_058",
        "title": "자유론"
      },
      {
        "book_id": "book_060",
        "title": "정신현상학"
      },
      {
        "book_id": "book_064",
        "title": "죽은 시인의 사회"
      }
    ]
  },
  {
    "major_id": "major_국어교육과",
    "display_name": "국어교육과",
    "bridge_key": "국어교육과",
    "bridge_confidence": "high",
    "book_candidates": [
      {
        "book_id": "book_064",
        "title": "죽은 시인의 사회"
      }
    ]
  },
  {
    "major_id": "major_기술교육과",
    "display_name": "기술교육과",
    "bridge_key": "교육",
    "bridge_confidence": "medium",
    "book_candidates": [
      {
        "book_id": "book_008",
        "title": "공정하다는 착각"
      },
      {
        "book_id": "book_demian",
        "title": "데미안"
      },
      {
        "book_id": "book_022",
        "title": "무정"
      },
      {
        "book_id": "book_024",
        "title": "미디어의 이해"
      },
      {
        "book_id": "book_025",
        "title": "반지성주의"
      },
      {
        "book_id": "book_026",
        "title": "백범일지"
      },
      {
        "book_id": "book_032",
        "title": "서유견문"
      },
      {
        "book_id": "book_058",
        "title": "자유론"
      },
      {
        "book_id": "book_060",
        "title": "정신현상학"
      },
      {
        "book_id": "book_064",
        "title": "죽은 시인의 사회"
      }
    ]
  },
  {
    "major_id": "major_독어교육과",
    "display_name": "독어교육과",
    "bridge_key": "교육",
    "bridge_confidence": "medium",
    "book_candidates": [
      {
        "book_id": "book_008",
        "title": "공정하다는 착각"
      },
      {
        "book_id": "book_demian",
        "title": "데미안"
      },
      {
        "book_id": "book_022",
        "title": "무정"
      },
      {
        "book_id": "book_024",
        "title": "미디어의 이해"
      },
      {
        "book_id": "book_025",
        "title": "반지성주의"
      },
      {
        "book_id": "book_026",
        "title": "백범일지"
      },
      {
        "book_id": "book_032",
        "title": "서유견문"
      },
      {
        "book_id": "book_058",
        "title": "자유론"
      },
      {
        "book_id": "book_060",
        "title": "정신현상학"
      },
      {
        "book_id": "book_064",
        "title": "죽은 시인의 사회"
      }
    ]
  },
  {
    "major_id": "major_물리교육과",
    "display_name": "물리교육과",
    "bridge_key": "교육",
    "bridge_confidence": "medium",
    "book_candidates": [
      {
        "book_id": "book_008",
        "title": "공정하다는 착각"
      },
      {
        "book_id": "book_demian",
        "title": "데미안"
      },
      {
        "book_id": "book_022",
        "title": "무정"
      },
      {
        "book_id": "book_024",
        "title": "미디어의 이해"
      },
      {
        "book_id": "book_025",
        "title": "반지성주의"
      },
      {
        "book_id": "book_026",
        "title": "백범일지"
      },
      {
        "book_id": "book_032",
        "title": "서유견문"
      },
      {
        "book_id": "book_058",
        "title": "자유론"
      },
      {
        "book_id": "book_060",
        "title": "정신현상학"
      },
      {
        "book_id": "book_064",
        "title": "죽은 시인의 사회"
      }
    ]
  },
  {
    "major_id": "major_미술교육과",
    "display_name": "미술교육과",
    "bridge_key": "교육",
    "bridge_confidence": "medium",
    "book_candidates": [
      {
        "book_id": "book_008",
        "title": "공정하다는 착각"
      },
      {
        "book_id": "book_demian",
        "title": "데미안"
      },
      {
        "book_id": "book_022",
        "title": "무정"
      },
      {
        "book_id": "book_024",
        "title": "미디어의 이해"
      },
      {
        "book_id": "book_025",
        "title": "반지성주의"
      },
      {
        "book_id": "book_026",
        "title": "백범일지"
      },
      {
        "book_id": "book_032",
        "title": "서유견문"
      },
      {
        "book_id": "book_058",
        "title": "자유론"
      },
      {
        "book_id": "book_060",
        "title": "정신현상학"
      },
      {
        "book_id": "book_064",
        "title": "죽은 시인의 사회"
      }
    ]
  },
  {
    "major_id": "major_불어교육과",
    "display_name": "불어교육과",
    "bridge_key": "교육",
    "bridge_confidence": "medium",
    "book_candidates": [
      {
        "book_id": "book_008",
        "title": "공정하다는 착각"
      },
      {
        "book_id": "book_demian",
        "title": "데미안"
      },
      {
        "book_id": "book_022",
        "title": "무정"
      },
      {
        "book_id": "book_024",
        "title": "미디어의 이해"
      },
      {
        "book_id": "book_025",
        "title": "반지성주의"
      },
      {
        "book_id": "book_026",
        "title": "백범일지"
      },
      {
        "book_id": "book_032",
        "title": "서유견문"
      },
      {
        "book_id": "book_058",
        "title": "자유론"
      },
      {
        "book_id": "book_060",
        "title": "정신현상학"
      },
      {
        "book_id": "book_064",
        "title": "죽은 시인의 사회"
      }
    ]
  },
  {
    "major_id": "major_사회교육과",
    "display_name": "사회교육과",
    "bridge_key": "사회교육과",
    "bridge_confidence": "high",
    "book_candidates": [
      {
        "book_id": "book_064",
        "title": "죽은 시인의 사회"
      }
    ]
  },
  {
    "major_id": "major_생물교육과",
    "display_name": "생물교육과",
    "bridge_key": "생물교육과",
    "bridge_confidence": "high",
    "book_candidates": [
      {
        "book_id": "book_053",
        "title": "이기적 유전자"
      },
      {
        "book_id": "book_063",
        "title": "종의 기원"
      }
    ]
  },
  {
    "major_id": "major_수학교육과",
    "display_name": "수학교육과",
    "bridge_key": "수학교육과",
    "bridge_confidence": "high",
    "book_candidates": [
      {
        "book_id": "book_003",
        "title": "객관성의 칼날"
      }
    ]
  },
  {
    "major_id": "major_역사교육과",
    "display_name": "역사교육과",
    "bridge_key": "역사교육과",
    "bridge_confidence": "high",
    "book_candidates": [
      {
        "book_id": "book_031",
        "title": "삼대"
      },
      {
        "book_id": "book_036",
        "title": "슬픈 열대"
      }
    ]
  },
  {
    "major_id": "major_영어교육과",
    "display_name": "영어교육과",
    "bridge_key": "교육",
    "bridge_confidence": "medium",
    "book_candidates": [
      {
        "book_id": "book_008",
        "title": "공정하다는 착각"
      },
      {
        "book_id": "book_demian",
        "title": "데미안"
      },
      {
        "book_id": "book_022",
        "title": "무정"
      },
      {
        "book_id": "book_024",
        "title": "미디어의 이해"
      },
      {
        "book_id": "book_025",
        "title": "반지성주의"
      },
      {
        "book_id": "book_026",
        "title": "백범일지"
      },
      {
        "book_id": "book_032",
        "title": "서유견문"
      },
      {
        "book_id": "book_058",
        "title": "자유론"
      },
      {
        "book_id": "book_060",
        "title": "정신현상학"
      },
      {
        "book_id": "book_064",
        "title": "죽은 시인의 사회"
      }
    ]
  },
  {
    "major_id": "major_유아교육학과",
    "display_name": "유아교육학과",
    "bridge_key": "교육",
    "bridge_confidence": "medium",
    "book_candidates": [
      {
        "book_id": "book_008",
        "title": "공정하다는 착각"
      },
      {
        "book_id": "book_demian",
        "title": "데미안"
      },
      {
        "book_id": "book_022",
        "title": "무정"
      },
      {
        "book_id": "book_024",
        "title": "미디어의 이해"
      },
      {
        "book_id": "book_025",
        "title": "반지성주의"
      },
      {
        "book_id": "book_026",
        "title": "백범일지"
      },
      {
        "book_id": "book_032",
        "title": "서유견문"
      },
      {
        "book_id": "book_058",
        "title": "자유론"
      },
      {
        "book_id": "book_060",
        "title": "정신현상학"
      },
      {
        "book_id": "book_064",
        "title": "죽은 시인의 사회"
      }
    ]
  },
  {
    "major_id": "major_윤리교육과",
    "display_name": "윤리교육과",
    "bridge_key": "윤리교육과",
    "bridge_confidence": "high",
    "book_candidates": [
      {
        "book_id": "book_021",
        "title": "맹자"
      },
      {
        "book_id": "book_041",
        "title": "아함경"
      },
      {
        "book_id": "book_051",
        "title": "의무론"
      },
      {
        "book_id": "book_056",
        "title": "인물로 읽는 장자"
      },
      {
        "book_id": "book_060",
        "title": "정신현상학"
      },
      {
        "book_id": "book_064",
        "title": "죽은 시인의 사회"
      },
      {
        "book_id": "book_065",
        "title": "짜라투스트라는 이렇게 말했다"
      }
    ]
  },
  {
    "major_id": "major_음악교육과",
    "display_name": "음악교육과",
    "bridge_key": "교육",
    "bridge_confidence": "medium",
    "book_candidates": [
      {
        "book_id": "book_008",
        "title": "공정하다는 착각"
      },
      {
        "book_id": "book_demian",
        "title": "데미안"
      },
      {
        "book_id": "book_022",
        "title": "무정"
      },
      {
        "book_id": "book_024",
        "title": "미디어의 이해"
      },
      {
        "book_id": "book_025",
        "title": "반지성주의"
      },
      {
        "book_id": "book_026",
        "title": "백범일지"
      },
      {
        "book_id": "book_032",
        "title": "서유견문"
      },
      {
        "book_id": "book_058",
        "title": "자유론"
      },
      {
        "book_id": "book_060",
        "title": "정신현상학"
      },
      {
        "book_id": "book_064",
        "title": "죽은 시인의 사회"
      }
    ]
  },
  {
    "major_id": "major_일반사회교육과",
    "display_name": "일반사회교육과",
    "bridge_key": "교육",
    "bridge_confidence": "medium",
    "book_candidates": [
      {
        "book_id": "book_008",
        "title": "공정하다는 착각"
      },
      {
        "book_id": "book_demian",
        "title": "데미안"
      },
      {
        "book_id": "book_022",
        "title": "무정"
      },
      {
        "book_id": "book_024",
        "title": "미디어의 이해"
      },
      {
        "book_id": "book_025",
        "title": "반지성주의"
      },
      {
        "book_id": "book_026",
        "title": "백범일지"
      },
      {
        "book_id": "book_032",
        "title": "서유견문"
      },
      {
        "book_id": "book_058",
        "title": "자유론"
      },
      {
        "book_id": "book_060",
        "title": "정신현상학"
      },
      {
        "book_id": "book_064",
        "title": "죽은 시인의 사회"
      }
    ]
  },
  {
    "major_id": "major_일어교육과",
    "display_name": "일어교육과",
    "bridge_key": "교육",
    "bridge_confidence": "medium",
    "book_candidates": [
      {
        "book_id": "book_008",
        "title": "공정하다는 착각"
      },
      {
        "book_id": "book_demian",
        "title": "데미안"
      },
      {
        "book_id": "book_022",
        "title": "무정"
      },
      {
        "book_id": "book_024",
        "title": "미디어의 이해"
      },
      {
        "book_id": "book_025",
        "title": "반지성주의"
      },
      {
        "book_id": "book_026",
        "title": "백범일지"
      },
      {
        "book_id": "book_032",
        "title": "서유견문"
      },
      {
        "book_id": "book_058",
        "title": "자유론"
      },
      {
        "book_id": "book_060",
        "title": "정신현상학"
      },
      {
        "book_id": "book_064",
        "title": "죽은 시인의 사회"
      }
    ]
  },
  {
    "major_id": "major_중국어교육과",
    "display_name": "중국어교육과",
    "bridge_key": "교육",
    "bridge_confidence": "medium",
    "book_candidates": [
      {
        "book_id": "book_008",
        "title": "공정하다는 착각"
      },
      {
        "book_id": "book_demian",
        "title": "데미안"
      },
      {
        "book_id": "book_022",
        "title": "무정"
      },
      {
        "book_id": "book_024",
        "title": "미디어의 이해"
      },
      {
        "book_id": "book_025",
        "title": "반지성주의"
      },
      {
        "book_id": "book_026",
        "title": "백범일지"
      },
      {
        "book_id": "book_032",
        "title": "서유견문"
      },
      {
        "book_id": "book_058",
        "title": "자유론"
      },
      {
        "book_id": "book_060",
        "title": "정신현상학"
      },
      {
        "book_id": "book_064",
        "title": "죽은 시인의 사회"
      }
    ]
  },
  {
    "major_id": "major_지구과학교육과",
    "display_name": "지구과학교육과",
    "bridge_key": "과학교육과",
    "bridge_confidence": "medium",
    "book_candidates": [
      {
        "book_id": "book_003",
        "title": "객관성의 칼날"
      },
      {
        "book_id": "book_028",
        "title": "부분과 전체"
      }
    ]
  },
  {
    "major_id": "major_지리교육과",
    "display_name": "지리교육과",
    "bridge_key": "교육",
    "bridge_confidence": "medium",
    "book_candidates": [
      {
        "book_id": "book_008",
        "title": "공정하다는 착각"
      },
      {
        "book_id": "book_demian",
        "title": "데미안"
      },
      {
        "book_id": "book_022",
        "title": "무정"
      },
      {
        "book_id": "book_024",
        "title": "미디어의 이해"
      },
      {
        "book_id": "book_025",
        "title": "반지성주의"
      },
      {
        "book_id": "book_026",
        "title": "백범일지"
      },
      {
        "book_id": "book_032",
        "title": "서유견문"
      },
      {
        "book_id": "book_058",
        "title": "자유론"
      },
      {
        "book_id": "book_060",
        "title": "정신현상학"
      },
      {
        "book_id": "book_064",
        "title": "죽은 시인의 사회"
      }
    ]
  },
  {
    "major_id": "major_체육교육과",
    "display_name": "체육교육과",
    "bridge_key": "교육",
    "bridge_confidence": "medium",
    "book_candidates": [
      {
        "book_id": "book_008",
        "title": "공정하다는 착각"
      },
      {
        "book_id": "book_demian",
        "title": "데미안"
      },
      {
        "book_id": "book_022",
        "title": "무정"
      },
      {
        "book_id": "book_024",
        "title": "미디어의 이해"
      },
      {
        "book_id": "book_025",
        "title": "반지성주의"
      },
      {
        "book_id": "book_026",
        "title": "백범일지"
      },
      {
        "book_id": "book_032",
        "title": "서유견문"
      },
      {
        "book_id": "book_058",
        "title": "자유론"
      },
      {
        "book_id": "book_060",
        "title": "정신현상학"
      },
      {
        "book_id": "book_064",
        "title": "죽은 시인의 사회"
      }
    ]
  },
  {
    "major_id": "major_초등교육과",
    "display_name": "초등교육과",
    "bridge_key": "교육",
    "bridge_confidence": "medium",
    "book_candidates": [
      {
        "book_id": "book_008",
        "title": "공정하다는 착각"
      },
      {
        "book_id": "book_demian",
        "title": "데미안"
      },
      {
        "book_id": "book_022",
        "title": "무정"
      },
      {
        "book_id": "book_024",
        "title": "미디어의 이해"
      },
      {
        "book_id": "book_025",
        "title": "반지성주의"
      },
      {
        "book_id": "book_026",
        "title": "백범일지"
      },
      {
        "book_id": "book_032",
        "title": "서유견문"
      },
      {
        "book_id": "book_058",
        "title": "자유론"
      },
      {
        "book_id": "book_060",
        "title": "정신현상학"
      },
      {
        "book_id": "book_064",
        "title": "죽은 시인의 사회"
      }
    ]
  },
  {
    "major_id": "major_컴퓨터교육과",
    "display_name": "컴퓨터교육과",
    "bridge_key": "교육",
    "bridge_confidence": "medium",
    "book_candidates": [
      {
        "book_id": "book_008",
        "title": "공정하다는 착각"
      },
      {
        "book_id": "book_demian",
        "title": "데미안"
      },
      {
        "book_id": "book_022",
        "title": "무정"
      },
      {
        "book_id": "book_024",
        "title": "미디어의 이해"
      },
      {
        "book_id": "book_025",
        "title": "반지성주의"
      },
      {
        "book_id": "book_026",
        "title": "백범일지"
      },
      {
        "book_id": "book_032",
        "title": "서유견문"
      },
      {
        "book_id": "book_058",
        "title": "자유론"
      },
      {
        "book_id": "book_060",
        "title": "정신현상학"
      },
      {
        "book_id": "book_064",
        "title": "죽은 시인의 사회"
      }
    ]
  },
  {
    "major_id": "major_특수교육과",
    "display_name": "특수교육과",
    "bridge_key": "교육",
    "bridge_confidence": "medium",
    "book_candidates": [
      {
        "book_id": "book_008",
        "title": "공정하다는 착각"
      },
      {
        "book_id": "book_demian",
        "title": "데미안"
      },
      {
        "book_id": "book_022",
        "title": "무정"
      },
      {
        "book_id": "book_024",
        "title": "미디어의 이해"
      },
      {
        "book_id": "book_025",
        "title": "반지성주의"
      },
      {
        "book_id": "book_026",
        "title": "백범일지"
      },
      {
        "book_id": "book_032",
        "title": "서유견문"
      },
      {
        "book_id": "book_058",
        "title": "자유론"
      },
      {
        "book_id": "book_060",
        "title": "정신현상학"
      },
      {
        "book_id": "book_064",
        "title": "죽은 시인의 사회"
      }
    ]
  },
  {
    "major_id": "major_한문교육과",
    "display_name": "한문교육과",
    "bridge_key": "교육",
    "bridge_confidence": "medium",
    "book_candidates": [
      {
        "book_id": "book_008",
        "title": "공정하다는 착각"
      },
      {
        "book_id": "book_demian",
        "title": "데미안"
      },
      {
        "book_id": "book_022",
        "title": "무정"
      },
      {
        "book_id": "book_024",
        "title": "미디어의 이해"
      },
      {
        "book_id": "book_025",
        "title": "반지성주의"
      },
      {
        "book_id": "book_026",
        "title": "백범일지"
      },
      {
        "book_id": "book_032",
        "title": "서유견문"
      },
      {
        "book_id": "book_058",
        "title": "자유론"
      },
      {
        "book_id": "book_060",
        "title": "정신현상학"
      },
      {
        "book_id": "book_064",
        "title": "죽은 시인의 사회"
      }
    ]
  },
  {
    "major_id": "major_화학교육과",
    "display_name": "화학교육과",
    "bridge_key": "교육",
    "bridge_confidence": "medium",
    "book_candidates": [
      {
        "book_id": "book_008",
        "title": "공정하다는 착각"
      },
      {
        "book_id": "book_demian",
        "title": "데미안"
      },
      {
        "book_id": "book_022",
        "title": "무정"
      },
      {
        "book_id": "book_024",
        "title": "미디어의 이해"
      },
      {
        "book_id": "book_025",
        "title": "반지성주의"
      },
      {
        "book_id": "book_026",
        "title": "백범일지"
      },
      {
        "book_id": "book_032",
        "title": "서유견문"
      },
      {
        "book_id": "book_058",
        "title": "자유론"
      },
      {
        "book_id": "book_060",
        "title": "정신현상학"
      },
      {
        "book_id": "book_064",
        "title": "죽은 시인의 사회"
      }
    ]
  },
  {
    "major_id": "major_환경교육과",
    "display_name": "환경교육과",
    "bridge_key": "교육",
    "bridge_confidence": "medium",
    "book_candidates": [
      {
        "book_id": "book_008",
        "title": "공정하다는 착각"
      },
      {
        "book_id": "book_demian",
        "title": "데미안"
      },
      {
        "book_id": "book_022",
        "title": "무정"
      },
      {
        "book_id": "book_024",
        "title": "미디어의 이해"
      },
      {
        "book_id": "book_025",
        "title": "반지성주의"
      },
      {
        "book_id": "book_026",
        "title": "백범일지"
      },
      {
        "book_id": "book_032",
        "title": "서유견문"
      },
      {
        "book_id": "book_058",
        "title": "자유론"
      },
      {
        "book_id": "book_060",
        "title": "정신현상학"
      },
      {
        "book_id": "book_064",
        "title": "죽은 시인의 사회"
      }
    ]
  }
]
