{
  "version": "1.25.0-cumulative",
  "patch_name": "assessment_engine_patch_cumulative_029schools_20260630",
  "generated_at": "2026-06-30T16:05:00+09:00",
  "purpose": "학교 수행평가 원자료를 학교명 의존 없이 수행평가 패턴 기반 보고서 주제 생성 엔진에 누적 반영한다.",
  "input_sources": [
    "sema_2026_g1_s1",
    "sema_2026_g2_s1",
    "sema_2026_g3_s1",
    "sema_2026_special_s1",
    "sejong_science_2026_g1_s1",
    "sejong_science_2026_g2_s1",
    "sejong_science_2026_g3_s1",
    "sejong_arts_2026_s1_b17fff18",
    "sejong_arts_2026_s1_31338d37",
    "sejong_arts_2026_s1_6f0d9c3a",
    "sejong_arts_2026_s1_b3b12236",
    "sejong_arts_2026_s1_372891e2",
    "sejong_arts_2026_s1_52bed016",
    "sejong_arts_2026_s1_78297d9a",
    "sejong_arts_2026_s1_525bfe6a",
    "sejong_arts_2026_s1_0ec9ca5d",
    "sejong_arts_2026_s1_ed25d661",
    "sejong_arts_2026_s1_e29adefc",
    "sejong_arts_2026_s1_e8a8a2db",
    "sejong_arts_2026_s1_4febba37",
    "sejong_arts_2026_s1_e63f8dc7",
    "sejong_arts_2026_s1_a6a459dc",
    "sejong_arts_2026_s1_ad5906a6",
    "sejong_arts_2026_s1_49abd7b9",
    "sejong_arts_2026_s1_d9b8423e",
    "sejong_arts_2026_s1_29e869c4",
    "sejong_arts_2026_s1_e0e56f7a",
    "sejong_arts_2026_s1_6472331f",
    "sejong_arts_2026_s1_57aea110",
    "sejong_arts_2026_s1_41cb3c30",
    "sejong_arts_2026_s1_09ed00dc",
    "sejong_arts_2026_s1_f0dda10d",
    "sejong_arts_2026_s1_a2d4c85e",
    "sejong_arts_2026_s1_a1739908",
    "sejong_arts_2026_s1_3ee72ce4",
    "sejong_arts_2026_s1_7258c71d",
    "sejong_arts_2026_s1_1b58589d",
    "sejong_arts_2026_s1_fa5df8d5",
    "sejong_arts_2026_s1_94c30dc1",
    "sejong_arts_2026_s1_3fbcb922",
    "sejong_arts_2026_s1_630be54f",
    "sejong_arts_2026_s1_99146fc1",
    "sejong_arts_2026_s1_2788ed11",
    "sejong_arts_2026_s1_5b818d01",
    "sejong_arts_2026_s1_7758319c",
    "sejong_arts_2026_s1_4bc6b643",
    "sejong_arts_2026_s1_2c3a2ad0",
    "sejong_arts_2026_s1_1e92a5b0",
    "sejong_arts_2026_s1_9baaf2b1",
    "sejong_arts_2026_s1_5913cddf",
    "sejong_arts_2026_s1_67a6e043",
    "sejong_arts_2026_s1_ac4b23bc",
    "sejong_arts_2026_s1_fbeb0986",
    "sejong_arts_2026_s1_bc21dc9a",
    "sejong_arts_2026_s1_64a1afc7",
    "sejong_arts_2026_s1_325735ee",
    "sejong_arts_2026_s1_0c1eddb2",
    "sejong_arts_2026_s1_5c8a31e0",
    "sejong_arts_2026_s1_2c8241a5",
    "sejong_arts_2026_s1_6d7b1a04",
    "sejong_arts_2026_s1_b37e9ff5",
    "sejong_arts_2026_s1_411eab7c",
    "sejong_arts_2026_s1_f09cbda2",
    "sejong_arts_2026_s1_82841a55",
    "sejong_arts_2026_s1_72a57519",
    "sejong_arts_2026_s1_3308e27c",
    "sejong_arts_2026_s1_2eaa8f01",
    "sejong_arts_2026_s1_80487a21",
    "sejong_arts_2026_s1_915ba140",
    "sejong_arts_2026_s1_3d12d1ae",
    "sejong_arts_2026_s1_2ae3f309",
    "sehwa_2026_g1_s1",
    "sehwa_2026_g2_s1",
    "sehwa_2026_g3_s1",
    "sehwa_girls_2026_g1_d24f7a",
    "sehwa_girls_2026_g2_c79555",
    "sehwa_girls_2026_g1_62f532",
    "sehwa_girls_2026_g1_9ead63",
    "sehwa_girls_2026_g1_1480d0",
    "sehwa_girls_2026_g1_735430",
    "sehwa_girls_2026_g2_ca5ecb",
    "sehwa_girls_2026_g2_013570",
    "sehwa_girls_2026_g2_85e3e5",
    "sehwa_girls_2026_g2_b46938",
    "sehwa_girls_2026_g2_14cb00",
    "sehwa_girls_2026_g2_439917",
    "sehwa_girls_2026_g2_1fcf5c",
    "sehwa_girls_2026_g3_135d9f",
    "sehwa_girls_2026_g3_09dda4",
    "sehwa_girls_2026_g3_018726",
    "sehwa_girls_2026_g3_5ae86f",
    "sehwa_girls_2026_g3_a0054f",
    "sehwa_girls_2026_g3_8fcb1e",
    "sehwa_girls_2026_g3_88d8eb",
    "sehwa_girls_2026_g3_aa3209",
    "sehwa_girls_2026_g3_164148",
    "sehwa_girls_2026_g3_3f5792",
    "sehwa_girls_2026_g3_cca385",
    "sehwa_girls_2026_g2_d16c7d",
    "sehwa_girls_2026_g1_aab960",
    "sehwa_girls_2026_g1_d0ad46",
    "sehwa_girls_2026_g1_4ab843",
    "sehwa_girls_2026_g1_55971c",
    "sehwa_girls_2026_g2_5d00aa",
    "sehwa_girls_2026_g2_695f07",
    "sehwa_girls_2026_g2_a20f08",
    "sehwa_girls_2026_g2_5cfdfc",
    "sehwa_girls_2026_g2_884409",
    "sehwa_girls_2026_g2_03e5ea",
    "sehwa_girls_2026_g2_7cfc04",
    "sehwa_girls_2026_g3_9ba312",
    "sehwa_girls_2026_g3_0afc14",
    "sehwa_girls_2026_g3_7b751e",
    "sehwa_girls_2026_g3_54c242",
    "sehwa_girls_2026_g3_30ee87",
    "sehwa_girls_2026_g3_13dd72",
    "sehwa_girls_2026_g3_0e6222",
    "sehwa_girls_2026_g3_d93ae7",
    "sehwa_girls_2026_g3_fae21d",
    "sehwa_girls_2026_g3_3797f3",
    "sehwa_girls_2026_g3_15792b",
    "sehwa_girls_2026_g1_0c661e",
    "sehwa_girls_2026_g2_2a48b1",
    "sehwa_girls_2026_g2_fa4790",
    "sehwa_girls_2026_g3_2a9d69",
    "ansan_dongsan_2026_g1_s1",
    "ansan_dongsan_2026_g2_s1",
    "ansan_dongsan_2026_g3_s1",
    "anyang_foreign_2026_g1_s1",
    "anyang_foreign_2026_g2_s1",
    "anyang_foreign_2026_g3_s1",
    "unjeong_2026_g1_s1_5f8fae",
    "unjeong_2026_g1_s1_0dc8b8",
    "unjeong_2026_g1_s1_990b78",
    "unjeong_2026_g1_s1_c6e102",
    "unjeong_2026_g1_s1_921bd6",
    "unjeong_2026_g1_s1_b85f32",
    "unjeong_2026_g1_s1_e9c1c4",
    "unjeong_2026_g1_s1_9a5af0",
    "unjeong_2026_g1_s1_2a327c",
    "unjeong_2026_g1_s1_dd15f3",
    "unjeong_2026_g1_s1_25b091",
    "unjeong_2026_g1_s1_163f01",
    "unjeong_2026_g2_s1_e8776d",
    "unjeong_2026_g2_s1_f1b53a",
    "unjeong_2026_g2_s1_7ac2b8",
    "unjeong_2026_g2_s1_f16c7f",
    "unjeong_2026_g2_s1_df3b0f",
    "unjeong_2026_g2_s1_ceda1e",
    "unjeong_2026_g2_s1_13281d",
    "unjeong_2026_g2_s1_fa7a12",
    "unjeong_2026_g2_s1_bb478e",
    "unjeong_2026_g2_s1_9aa393",
    "unjeong_2026_g2_s1_c8feb4",
    "unjeong_2026_g2_s1_14eb97",
    "unjeong_2026_g2_s1_b47b99",
    "unjeong_2026_g2_s1_82def6",
    "unjeong_2026_g2_s1_fceba8",
    "unjeong_2026_g2_s1_890de1",
    "unjeong_2026_g2_s1_cc86f9",
    "unjeong_2026_g2_s1_5db67d",
    "unjeong_2026_g2_s1_e31669",
    "unjeong_2026_g3_s1_c54cb8",
    "unjeong_2026_g3_s1_80b535",
    "unjeong_2026_g3_s1_fe4d6c",
    "unjeong_2026_g3_s1_50ba55",
    "unjeong_2026_g3_s1_7adc44",
    "unjeong_2026_g3_s1_2e07ef",
    "unjeong_2026_g3_s1_b635eb",
    "unjeong_2026_g3_s1_b64d6e",
    "unjeong_2026_g3_s1_f10298",
    "unjeong_2026_g3_s1_6cdf95",
    "unjeong_2026_g3_s1_c415d9",
    "unjeong_2026_g3_s1_98bd06",
    "unjeong_2026_g3_s1_6af462",
    "unjeong_2026_g3_s1_6e54b8",
    "unjeong_2026_g3_s1_f5e4b8",
    "unjeong_2026_g3_s1_f56be4",
    "unjeong_2026_g3_s1_59455c",
    "unjeong_2026_g3_s1_7f9443",
    "unjeong_2026_g3_s1_af3782",
    "unjeong_2026_g3_s1_137e2e",
    "unjeong_2026_g3_s1_064d4d",
    "unjeong_2026_g3_s1_7573b4",
    "unjeong_2026_g3_s1_f73976",
    "ulsan_science_2026_g1_s1_29cd65",
    "ulsan_science_2026_g1_s1_2ff702",
    "ulsan_science_2026_g1_s1_7b2fc6",
    "ulsan_science_2026_g1_s1_bf5203",
    "ulsan_science_2026_g1_s1_e7566f",
    "ulsan_science_2026_g1_s1_225eeb",
    "ulsan_science_2026_g1_s1_3dbc55",
    "ulsan_science_2026_g1_s1_a1c394",
    "ulsan_science_2026_g1_s1_ff56da",
    "ulsan_science_2026_g1_s1_1e0496",
    "ulsan_science_2026_g1_s1_d98676",
    "ulsan_science_2026_g2_s1_e42877",
    "ulsan_science_2026_g2_s1_22e02a",
    "ulsan_science_2026_g2_s1_5023d5",
    "ulsan_science_2026_g2_s1_8d9e41",
    "ulsan_science_2026_g2_s1_69e27f",
    "ulsan_science_2026_g2_s1_076e2f",
    "ulsan_science_2026_g2_s1_b37715",
    "ulsan_science_2026_g2_s1_da78e7",
    "ulsan_science_2026_g2_s1_f745f9",
    "ulsan_science_2026_g2_s1_7228d0",
    "ulsan_science_2026_g3_s1_d46fc0",
    "ulsan_science_2026_g3_s1_f0e8cc",
    "ulsan_science_2026_g3_s1_4b6356",
    "ulsan_science_2026_g3_s1_5859b6",
    "ulsan_science_2026_g3_s1_fd064d",
    "ulsan_science_2026_g3_s1_5b95ee",
    "ulsan_science_2026_g3_s1_b176fe",
    "ulsan_science_2026_g3_s1_2f9b40",
    "ulsan_science_2026_g3_s1_c6d60b",
    "ulsan_science_2026_g3_s1_034853",
    "ulsan_science_2026_g3_s1_b4072b",
    "ulsan_science_2026_g3_s1_591a19",
    "ulsan_science_2026_g3_s1_aa714f",
    "ulsan_science_2026_g3_s1_997610",
    "gwangju_science_2026_g1_s1_9b32254101",
    "gwangju_science_2026_g1_s1_14d59cbbf9",
    "gwangju_science_2026_g1_s1_4ade722193",
    "gwangju_science_2026_g1_s1_39395fab4e",
    "gwangju_science_2026_g1_s1_c38f87ebc6",
    "gwangju_science_2026_g1_s1_c54715b08a",
    "gwangju_science_2026_g1_s1_85b47cf78b",
    "gwangju_science_2026_g1_s1_f9ef031d4f",
    "gwangju_science_2026_g1_s1_b904216a65",
    "gwangju_science_2026_g1_s1_831bca773e",
    "gwangju_science_2026_g1_s1_3286555e51",
    "gwangju_science_2026_g1_s1_7a601c24f4",
    "gwangju_science_2026_g1_s1_16d0b97631",
    "gwangju_science_2026_g1_s1_838c1f70b1",
    "gwangju_science_2026_g1_s1_16a15429f7",
    "gwangju_science_2026_g2_s1_0056dcd10b",
    "gwangju_science_2026_g2_s1_3856a28ddc",
    "gwangju_science_2026_g2_s1_3c28fa3229",
    "gwangju_science_2026_g2_s1_dbba046bd8",
    "gwangju_science_2026_g2_s1_3c66c1f6f3",
    "gwangju_science_2026_g2_s1_9553dbd20b",
    "gwangju_science_2026_g2_s1_e4e99cc36b",
    "gwangju_science_2026_g2_s1_df4e45a731",
    "gwangju_science_2026_g2_s1_dd2383d8a8",
    "gwangju_science_2026_g2_s1_280fd2dc86",
    "gwangju_science_2026_g2_s1_9c7f4e9997",
    "gwangju_science_2026_g3_s1_bca6689d76",
    "gwangju_science_2026_g3_s1_69d07cf402",
    "gwangju_science_2026_g3_s1_7d1c5202ba",
    "gwangju_science_2026_g3_s1_b106199705",
    "gwangju_science_2026_g3_s1_0d3e1dca7c",
    "gwangju_science_2026_g3_s1_113de7c53d",
    "gwangju_science_2026_g3_s1_5629555858",
    "gwangju_science_2026_g3_s1_0ea6711b79",
    "gwangju_science_2026_g3_s1_0d0fa0fbff",
    "gwangju_science_2026_g3_s1_b7dec22329",
    "gwangju_science_2026_g3_s1_99537a6f94",
    "gwangju_science_2026_g3_s1_4a37d5bdcb",
    "gwangju_science_2026_g3_s1_81bccc44b1",
    "gwangju_science_2026_g3_s1_de9741bc6c",
    "gwangju_science_2026_g3_s1_eb78c7a3ff",
    "gwangju_science_2026_g3_s1_c59c8ed925",
    "gwangju_science_2026_g3_s1_41bd640de1",
    "gwangju_science_2026_g3_s1_1805168c6a",
    "gwangju_science_2026_g3_s1_37675f7944",
    "gwangju_science_2026_g3_s1_a46337358c",
    "gwangju_science_2026_g3_s1_aec4ef06f7",
    "gwangju_science_2026_g3_s1_e6becfde64",
    "gwangju_science_2026_g3_s1_4ff2544167",
    "gwangju_science_2026_g3_s1_c828fa2ab1",
    "gwangju_science_2026_g3_s1_7ea14d3c90",
    "gwangju_science_2026_g3_s1_cdfd0234a0",
    "gwangju_science_2026_g3_s1_6afac11114",
    "gwangju_science_2026_g3_s1_9dc8f91dfa",
    "gwangju_science_2026_g3_s1_2872811e39",
    "gwangju_science_2026_g2_s1_40f35096fe",
    "kimcheon_2026_g1_s1_ac7e34a690",
    "kimcheon_2026_g1_s1_00c7a085a0",
    "kimcheon_2026_g1_s1_eec73432c3",
    "kimcheon_2026_g1_s1_4bbc5ae542",
    "kimcheon_2026_g1_s1_9ce116e948",
    "kimcheon_2026_g1_s1_f83ac62918",
    "kimcheon_2026_g1_s1_87f803786d",
    "kimcheon_2026_g1_s1_38498439df",
    "kimcheon_2026_g1_s1_5b2bc6d8fc",
    "kimcheon_2026_g1_s1_a0b3a159d5",
    "kimcheon_2026_g1_s1_8c89689f5b",
    "kimcheon_2026_g2_s1_e13793dca7",
    "kimcheon_2026_g2_s1_8c1c6a3152",
    "kimcheon_2026_g2_s1_c063a1e48d",
    "kimcheon_2026_g2_s1_c43559e0d4",
    "kimcheon_2026_g2_s1_592c4bdf44",
    "kimcheon_2026_g2_s1_2eb7bac825",
    "kimcheon_2026_g2_s1_6a1829e0bc",
    "kimcheon_2026_g2_s1_5e6dd0a4a0",
    "kimcheon_2026_g2_s1_4c667b0173",
    "kimcheon_2026_g2_s1_4727fdad7a",
    "kimcheon_2026_g2_s1_d52dba6f9b",
    "kimcheon_2026_g2_s1_93e9ca865c",
    "kimcheon_2026_g2_s1_92927aaf8b",
    "kimcheon_2026_g2_s1_cf4f884e5f",
    "kimcheon_2026_g2_s1_089be4876b",
    "kimcheon_2026_g2_s1_7605e09d44",
    "kimcheon_2026_g2_s1_c742ca3e8a",
    "kimcheon_2026_g2_s1_14c747bff3",
    "kimcheon_2026_g2_s1_25dc6e6b86",
    "kimcheon_2026_g3_s1_c2fbfb533f",
    "kimcheon_2026_g3_s1_bd0a098037",
    "kimcheon_2026_g3_s1_6d2c569b14",
    "kimcheon_2026_g3_s1_9e506a211a",
    "kimcheon_2026_g3_s1_ca50febf14",
    "kimcheon_2026_g3_s1_082a1c52de",
    "kimcheon_2026_g3_s1_c8718b8fda",
    "kimcheon_2026_g3_s1_3a4b6d3051",
    "kimcheon_2026_g3_s1_99c7caa777",
    "kimcheon_2026_g3_s1_81c3b375f3",
    "kimcheon_2026_g3_s1_aebddcb10b",
    "kimcheon_2026_g3_s1_f37aab9f1f",
    "kimcheon_2026_g3_s1_ec9396aa3b",
    "kimcheon_2026_g3_s1_de68ec6ac0",
    "kimcheon_2026_g3_s1_e85c24a5da",
    "kimcheon_2026_g3_s1_f7c02a3ba8",
    "kimcheon_2026_g3_s1_eda28f03ea",
    "kimcheon_2026_g3_s1_2d3cba7ef9",
    "kimcheon_2026_g3_s1_da5bcd064b",
    "daegun_2026_g1_s1",
    "daegun_2026_g2_s1",
    "daegun_2026_g3_s1",
    "daegun_2026_joint_s1",
    "daegu_science_2026_s1_g123",
    "daegu_il_science_2026_g1_s1",
    "daegu_il_science_2026_g2_s1",
    "daegu_il_science_2026_g3_s1",
    "daewon_foreign_2026_g1_s1",
    "daewon_foreign_2026_g2_s1",
    "daewon_foreign_2026_g3_s1",
    "daeil_foreign_2026_g1_s1_b74d12fd",
    "daeil_foreign_2026_g1_s1_1be6d9b7",
    "daeil_foreign_2026_g1_s1_a2c71307",
    "daeil_foreign_2026_g1_s1_647b1d14",
    "daeil_foreign_2026_g1_s1_1d364f78",
    "daeil_foreign_2026_g1_s1_db6b6abd",
    "daeil_foreign_2026_g1_s1_dd233ff3",
    "daeil_foreign_2026_g1_s1_99e2a2b4",
    "daeil_foreign_2026_g1_s1_ca356e77",
    "daeil_foreign_2026_g1_s1_c90de0c6",
    "daeil_foreign_2026_g1_s1_24044762",
    "daeil_foreign_2026_g1_s1_18d0a9b6",
    "daeil_foreign_2026_g1_s1_113383ff",
    "daeil_foreign_2026_g1_s1_a0a2d799",
    "daeil_foreign_2026_g1_s1_977571f7",
    "daeil_foreign_2026_g1_s1_30b6464b",
    "daeil_foreign_2026_g2_s1_2d826da2",
    "daeil_foreign_2026_g2_s1_736e3f63",
    "daeil_foreign_2026_g2_s1_4e961758",
    "daeil_foreign_2026_g2_s1_ea9cc3d8",
    "daeil_foreign_2026_g2_s1_06248581",
    "daeil_foreign_2026_g2_s1_0600d68a",
    "daeil_foreign_2026_g2_s1_73e2472e",
    "daeil_foreign_2026_g2_s1_5560cb7c",
    "daeil_foreign_2026_g2_s1_1d3773ef",
    "daeil_foreign_2026_g2_s1_95755661",
    "daeil_foreign_2026_g2_s1_068df2c7",
    "daeil_foreign_2026_g2_s1_0cdd9d90",
    "daeil_foreign_2026_g2_s1_d03a2be5",
    "daeil_foreign_2026_g2_s1_a6740d38",
    "daeil_foreign_2026_g2_s1_41b38820",
    "daeil_foreign_2026_g2_s1_4afd2024",
    "daeil_foreign_2026_g3_s1_6d12af83",
    "daeil_foreign_2026_g3_s1_c85604c6",
    "daeil_foreign_2026_g3_s1_a611ad4a",
    "daeil_foreign_2026_g3_s1_315ab9d1",
    "daeil_foreign_2026_g3_s1_3d4d9ca4",
    "daeil_foreign_2026_g3_s1_0a853fc8",
    "daeil_foreign_2026_g3_s1_279730bb",
    "daeil_foreign_2026_g3_s1_30d05e76",
    "daeil_foreign_2026_g3_s1_9ed56814",
    "daeil_foreign_2026_g3_s1_bc163d44",
    "daeil_foreign_2026_g3_s1_13e90adc",
    "daeil_foreign_2026_g3_s1_265cdb9a",
    "daeil_foreign_2026_g3_s1_85295f56",
    "daeil_foreign_2026_g3_s1_816b7e1d",
    "daeil_foreign_2026_g3_s1_ca086b11",
    "daejeon_science_2026_g1_s1",
    "daejeon_science_2026_g2_s1",
    "daejeon_science_2026_g3_s1",
    "daejeon_daeseong_2026_g1_s1",
    "daejeon_daeseong_2026_g2_s1",
    "daejeon_daeseong_2026_g3_s1",
    "daejeon_daeseong_2026_joint_s1",
    "daejeon_dongshin_science_2026_g1_s1",
    "daejeon_dongshin_science_2026_g2_s1",
    "daejeon_dongshin_science_2026_g3_s1",
    "daejeon_foreign_2026_g1_s1",
    "daejeon_foreign_2026_g2_s1",
    "daejeon_foreign_2026_g3_s1",
    "daejeon_foreign_2026_joint_s1",
    "minsago_2026_g1_s1_21062f87",
    "minsago_2026_g1_s1_f4679d29",
    "minsago_2026_g1_s1_7d524bb1",
    "minsago_2026_g1_s1_9b392854",
    "minsago_2026_g1_s1_1becf1d8",
    "minsago_2026_g1_s1_6ca7ae68",
    "minsago_2026_g1_s1_d033272d",
    "minsago_2026_g1_s1_c892ccfe",
    "minsago_2026_g1_s1_60ef0ae9",
    "minsago_2026_g1_s1_531abe18",
    "minsago_2026_g1_s1_b5c44f69",
    "minsago_2026_g1_s1_acae4016",
    "minsago_2026_g1_s1_d25150a4",
    "minsago_2026_g1_s1_ee4e5a5a",
    "minsago_2026_g1_s1_55631d2e",
    "minsago_2026_g1_s1_eef205f6",
    "minsago_2026_g1_s1_57a74d65",
    "minsago_2026_g1_s1_1114c429",
    "minsago_2026_g1_s1_fb5b362a",
    "minsago_2026_g1_s1_b104e0ed",
    "minsago_2026_g1_s1_24b0fa50",
    "minsago_2026_g1_s1_ec40c503",
    "minsago_2026_g1_s1_d30f98a0",
    "minsago_2026_g1_s1_634d2e73",
    "minsago_2026_g1_s1_e06f78b3",
    "minsago_2026_g1_s1_97ee7280",
    "minsago_2026_g1_s1_06ff4165",
    "minsago_2026_g1_s1_26759d35",
    "minsago_2026_g1_s1_8f8548cb",
    "minsago_2026_g1_s1_389b8544",
    "minsago_2026_g1_s1_6f6fdbe1",
    "minsago_2026_g1_s1_b8be82f1",
    "minsago_2026_g1_s1_6196bbb9",
    "minsago_2026_g1_s1_fcd9fae4",
    "minsago_2026_g2_s1_b54fd6b5",
    "minsago_2026_g2_s1_d9750e97",
    "minsago_2026_g2_s1_a77fe402",
    "minsago_2026_g2_s1_63193762",
    "minsago_2026_g2_s1_39093aa4",
    "minsago_2026_g2_s1_719d60bf",
    "minsago_2026_g2_s1_ed57670b",
    "minsago_2026_g2_s1_799c2099",
    "minsago_2026_g2_s1_b05ffbcf",
    "minsago_2026_g2_s1_844a7032",
    "minsago_2026_g2_s1_aeb0e067",
    "minsago_2026_g2_s1_e12bdd75",
    "minsago_2026_g2_s1_6a695143",
    "minsago_2026_g2_s1_0556a16b",
    "minsago_2026_g2_s1_68af7d9a",
    "minsago_2026_g2_s1_c66dc888",
    "minsago_2026_g2_s1_b29d1285",
    "minsago_2026_g2_s1_8a0e9930",
    "minsago_2026_g2_s1_cb992deb",
    "minsago_2026_g2_s1_a2866994",
    "minsago_2026_g2_s1_cc2037a6",
    "minsago_2026_g2_s1_84c5d755",
    "minsago_2026_g2_s1_8f1b3777",
    "minsago_2026_g2_s1_956ddec0",
    "minsago_2026_g2_s1_bab14b8e",
    "minsago_2026_g2_s1_ca666886",
    "minsago_2026_g2_s1_04fa8730",
    "minsago_2026_g2_s1_aabb7262",
    "minsago_2026_g2_s1_b3a46a61",
    "minsago_2026_g2_s1_5f88b9b5",
    "minsago_2026_g2_s1_0f8ad7f5",
    "minsago_2026_g2_s1_37dc133d",
    "minsago_2026_g2_s1_37cb72db",
    "minsago_2026_g2_s1_b2332a11",
    "minsago_2026_g2_s1_e282667f",
    "minsago_2026_g2_s1_8aa0ee69",
    "minsago_2026_g2_s1_571eb5d3",
    "minsago_2026_g2_s1_67a44c3e",
    "minsago_2026_g2_s1_aa5fd383",
    "minsago_2026_g2_s1_22d3fb8c",
    "minsago_2026_g2_s1_7183fdf9",
    "minsago_2026_g2_s1_1dbf0813",
    "minsago_2026_g2_s1_50a5c217",
    "minsago_2026_g2_s1_d76a21d1",
    "minsago_2026_g2_s1_41d04f28",
    "minsago_2026_g2_s1_9b3738ad",
    "minsago_2026_g2_s1_96634745",
    "minsago_2026_g2_s1_a3d23aa8",
    "minsago_2026_g3_s1_85d83be9",
    "minsago_2026_g3_s1_2664a656",
    "minsago_2026_g3_s1_6a540eff",
    "minsago_2026_g3_s1_c3a8e8de",
    "minsago_2026_g3_s1_2a2c5474",
    "minsago_2026_g3_s1_302363f2",
    "minsago_2026_g3_s1_a599926b",
    "minsago_2026_g3_s1_23f1bbb6",
    "minsago_2026_g3_s1_5c111e7e",
    "minsago_2026_g3_s1_13994709",
    "minsago_2026_g3_s1_3dcd4176",
    "minsago_2026_g3_s1_1d85bae5",
    "minsago_2026_g3_s1_3eddcaec",
    "minsago_2026_g3_s1_bc41b8d2",
    "minsago_2026_g3_s1_4cc8880e",
    "minsago_2026_g3_s1_a42f4407",
    "minsago_2026_g3_s1_c067a018",
    "minsago_2026_g3_s1_8b9513fc",
    "minsago_2026_g3_s1_c80fdeb4",
    "minsago_2026_g3_s1_d12a1211",
    "minsago_2026_g3_s1_527338b9",
    "minsago_2026_g3_s1_59099280",
    "minsago_2026_g3_s1_541d71fa",
    "minsago_2026_g3_s1_c3e4e426",
    "minsago_2026_g3_s1_d802b8f5",
    "minsago_2026_g3_s1_b8982822",
    "minsago_2026_g3_s1_47b222b1",
    "minsago_2026_g3_s1_d9b023e3",
    "minsago_2026_g3_s1_de40bc7f",
    "minsago_2026_g3_s1_b32a7035",
    "minsago_2026_g3_s1_3fa156df",
    "minsago_2026_g3_s1_2157553e",
    "minsago_2026_g3_s1_d0b8a981",
    "minsago_2026_g3_s1_8fcf78ec",
    "minsago_2026_g3_s1_482ee1cf",
    "minsago_2026_g3_s1_159715a4",
    "minsago_2026_g3_s1_0d6c1c7a",
    "minsago_2026_g3_s1_155b9710",
    "minsago_2026_g3_s1_c84f0f31",
    "minsago_2026_g3_s1_c44258fe",
    "minsago_2026_g3_s1_c06b27ce",
    "minsago_2026_g3_s1_d17314ec",
    "minsago_2026_g3_s1_75d43629",
    "minsago_2026_g3_s1_e7a1fa6b",
    "minsago_2026_g3_s1_8a0a6d63",
    "minsago_2026_g3_s1_2625e05c",
    "minsago_2026_g3_s1_839ba308",
    "minsago_2026_g3_s1_80863fcb",
    "minsago_2026_g3_s1_ceea1947",
    "minsago_2026_g3_s1_8500d92b",
    "minsago_2026_g3_s1_99c160db",
    "minsago_2026_g3_s1_a4cba980",
    "minsago_2026_g3_s1_7cdd7492",
    "minsago_2026_g3_s1_fab2af61",
    "minsago_2026_g3_s1_c177c6a6",
    "minsago_2026_g3_s1_bb9ee327",
    "minsago_2026_g3_s1_18890570",
    "minsago_2026_g3_s1_f3f83ac2",
    "minsago_2026_g3_s1_60f168fe",
    "minsago_2026_g3_s1_6593f9d7",
    "minsago_2026_g3_s1_56e674f1",
    "minsago_2026_g3_s1_409855dd",
    "minsago_2026_g3_s1_b75442cd",
    "minsago_2026_g3_s1_09e678d7",
    "minsago_2026_g3_s1_e614b576",
    "bukil_2026_g1_s1",
    "bukil_2026_g2_s1",
    "bukil_2026_g3_s1",
    "seorabeol_2026_g1_s1_07335440",
    "seorabeol_2026_g1_s1_0f00df95",
    "seorabeol_2026_g1_s1_70eaf013",
    "seorabeol_2026_g1_s1_3a3c1d19",
    "seorabeol_2026_g1_s1_b26dd2e2",
    "seorabeol_2026_g1_s1_c6e52ed6",
    "seorabeol_2026_g1_s1_dd772e76",
    "seorabeol_2026_g1_s1_df5fd456",
    "seorabeol_2026_g1_s1_9f3756ec",
    "seorabeol_2026_g1_s1_d3d3ee58",
    "seorabeol_2026_g1_s1_e590a3d6",
    "seorabeol_2026_g2_s1_a5161915",
    "seorabeol_2026_g2_s1_810abb9f",
    "seorabeol_2026_g2_s1_d13e122f",
    "seorabeol_2026_g2_s1_5fc57c42",
    "seorabeol_2026_g2_s1_01f257dc",
    "seorabeol_2026_g2_s1_be7b0ac7",
    "seorabeol_2026_g2_s1_d2ac441a",
    "seorabeol_2026_g2_s1_2c25c1e9",
    "seorabeol_2026_g2_s1_e00cd2a7",
    "seorabeol_2026_g2_s1_516f1fb8",
    "seorabeol_2026_g2_s1_c01f1c39",
    "seorabeol_2026_g2_s1_5ae007d3",
    "seorabeol_2026_g2_s1_185af2b8",
    "seorabeol_2026_g2_s1_f3e73bc7",
    "seorabeol_2026_g2_s1_0b4774ab",
    "seorabeol_2026_g2_s1_76b55c28",
    "seorabeol_2026_g2_s1_e107559d",
    "seorabeol_2026_g2_s1_412431af",
    "seorabeol_2026_g2_s1_e38ce87d",
    "seorabeol_2026_g2_s1_7736b35a",
    "seorabeol_2026_g3_s1_676869aa",
    "seorabeol_2026_g3_s1_659bcdab",
    "seorabeol_2026_g3_s1_328bdd2f",
    "seorabeol_2026_g3_s1_8e286f11",
    "seorabeol_2026_g3_s1_44073c90",
    "seorabeol_2026_g3_s1_7b3bb988",
    "seorabeol_2026_g3_s1_d308d57c",
    "seorabeol_2026_g3_s1_62c99a11",
    "seorabeol_2026_g3_s1_c4695ab3",
    "seorabeol_2026_g3_s1_5555da16",
    "seorabeol_2026_g3_s1_28f625c4",
    "seorabeol_2026_g3_s1_bcbf7be4",
    "seorabeol_2026_g3_s1_9dd522d0",
    "seorabeol_2026_g3_s1_8263c211",
    "seorabeol_2026_g3_s1_5abbc913",
    "seorabeol_2026_g3_s1_d18cdf77",
    "seorabeol_2026_g3_s1_f66c4a40",
    "seorabeol_2026_g3_s1_ce7f5f44",
    "seorabeol_2026_g3_s1_17435475",
    "seorabeol_2026_g3_s1_e959c2ce",
    "seorabeol_2026_g3_s1_63d64077",
    "seorabeol_2026_g3_s1_70e72d9f",
    "seorabeol_2026_g3_s1_aaa53cc4",
    "seorabeol_2026_g3_s1_ac8705bf",
    "seorabeol_2026_g3_s1_4fa8d8d7",
    "seorabeol_2026_g3_s1_13340356",
    "seorabeol_2026_g3_s1_c84eaf6a",
    "seorabeol_2026_g3_s1_aff233ec",
    "seorabeol_2026_g3_s1_a122c2cc",
    "seorabeol_2026_g3_s1_1ab5f10c",
    "seorabeol_2026_g3_s1_f0d465cf",
    "seoul_science_2026_s1_g123",
    "2026학년도 1학기 선덕고 과학정보과 교수·학습 및 평가계획.pdf",
    "2026학년도 1학기 선덕고 교양과목 교수·학습 및 평가계획.pdf",
    "2026학년도 1학기 선덕고 국어과 교수·학습 및 평가계획.pdf",
    "2026학년도 1학기 선덕고 사회과 교수·학습 및 평가계획.pdf",
    "2026학년도 1학기 선덕고 수학과 교수·학습 및 평가계획.pdf",
    "2026학년도 1학기 선덕고 영어과 교수·학습 및 평가계획.pdf",
    "2026학년도 1학기 선덕고 예술체육과 교수·학습 및 평가계획.pdf",
    "2026학년도 1학기 선덕고 한문 교수·학습 및 평가계획.pdf",
    "2026학년도 1학기 교수학습 및 평가계획(정보공시).pdf",
    "2026학년도 1학기 교수학습 및 평가운영계획(최종본).pdf",
    "gyeonggi_foreign_2026_g1_s1_727a32ea",
    "gyeonggi_foreign_2026_g1_s1_97bf9724",
    "gyeonggi_foreign_2026_g1_s1_01779c2d",
    "gyeonggi_foreign_2026_g1_s1_11701b3c",
    "gyeonggi_foreign_2026_g1_s1_d29d1885",
    "gyeonggi_foreign_2026_g1_s1_00b6c64e",
    "gyeonggi_foreign_2026_g1_s1_a64276cc",
    "gyeonggi_foreign_2026_g1_s1_dc4d03c4",
    "gyeonggi_foreign_2026_g1_s1_2d5d2fc3",
    "gyeonggi_foreign_2026_g1_s1_dc9ade6b",
    "gyeonggi_foreign_2026_g1_s1_f1f38f1d",
    "gyeonggi_foreign_2026_g1_s1_b7d8b1a1",
    "gyeonggi_foreign_2026_g1_s1_a5234019",
    "gyeonggi_foreign_2026_g2_s1_4fac8127",
    "gyeonggi_foreign_2026_g2_s1_412201f4",
    "gyeonggi_foreign_2026_g2_s1_691ab955",
    "gyeonggi_foreign_2026_g2_s1_caacac66",
    "gyeonggi_foreign_2026_g2_s1_8f511de4",
    "gyeonggi_foreign_2026_g2_s1_d65472ac",
    "gyeonggi_foreign_2026_g2_s1_30b01641",
    "gyeonggi_foreign_2026_g2_s1_ccfa947a",
    "gyeonggi_foreign_2026_g2_s1_e269afca",
    "gyeonggi_foreign_2026_g2_s1_daf68ade",
    "gyeonggi_foreign_2026_g2_s1_83e22fd9",
    "gyeonggi_foreign_2026_g2_s1_6e9897fe",
    "gyeonggi_foreign_2026_g2_s1_17cdca54",
    "gyeonggi_foreign_2026_g3_s1_1dbecfc9",
    "gyeonggi_foreign_2026_g3_s1_4ca09d02",
    "gyeonggi_foreign_2026_g3_s1_103b9314",
    "gyeonggi_foreign_2026_g3_s1_c9014014",
    "gyeonggi_foreign_2026_g3_s1_3ddc7ee1",
    "gyeonggi_foreign_2026_g3_s1_2280158b",
    "gyeonggi_foreign_2026_g3_s1_5f3ebeee",
    "gyeonggi_foreign_2026_g3_s1_2256e4b1",
    "gyeonggi_foreign_2026_g3_s1_27e9aa62",
    "gyeonggi_foreign_2026_g3_s1_8d004143",
    "gyeonggi_foreign_2026_g3_s1_d18a4988",
    "gyeonggi_foreign_2026_g3_s1_6f443997",
    "gyeonggi_foreign_2026_g3_s1_b6f05b44",
    "gyeonggi_foreign_2026_g3_s1_ab87205f",
    "gyeonggi_foreign_2026_g3_s1_3d39fade",
    "gyeonggi_foreign_2026_g3_s1_5d500558",
    "gyeonggi_foreign_2026_g3_s1_977e76f3",
    "gyeonggi_foreign_2026_g3_s1_e6846595",
    "gyeongnam_foreign_2026_g1_s1",
    "gyeongnam_foreign_2026_g2_s1",
    "gyeongnam_foreign_2026_g3_s1"
  ],
  "newly_added_school": "경남외고",
  "newly_added_tasks": 68,
  "newly_added_topic_generating_tasks": 65,
  "newly_added_non_topic_generating_tasks": 3,
  "total_assessment_tasks": 3906,
  "topic_generating_tasks": 3142,
  "non_topic_generating_tasks": 764,
  "standard_subject_count": 710,
  "source_count": 667,
  "runtime_school_name_policy": "school_name은 원자료 추적 및 검수용으로만 유지하고, 런타임 주제 생성은 subject_group/content_axis/method_axis/output_axis/report_mode/topic_formula 중심으로 수행한다.",
  "latest_input_bundle": "경남외고 수행평가.zip",
  "latest_source_pdf_count": 3,
  "previous_patch": "assessment_engine_patch_cumulative_028schools_20260630",
  "latest_source_file_count": 3,
  "latest_source_hwp_count": 0,
  "latest_source_hwpx_count": 0,
  "latest_source_pdf_page_count": 442,
  "latest_source_subject_count": 32,
  "latest_patch_docs": []
}
